measure/cam2disp_measure/cores/uart_t/rtl/nuart_tx.v
module nuart_tx(clk_i, rst_n_i, tx_timing_i, txd_o, fifo_rd_o, fifo_data_i, fifo_empty_i);
	input clk_i;
	input rst_n_i;
	input tx_timing_i;
	output txd_o;
	output fifo_rd_o;
	input [7:0] fifo_data_i;
	input fifo_empty_i;

	//bit[9]:start bit, bit[8:1]:tx data, bit[0]:stop bit.
	reg [9:0] tx_buf_r;  
	reg [3:0] state;
	reg [3:0] tx_cnt;

	reg 			fifo_rd_r;
	reg 			txd_r;
	
  parameter IDLE_STATE = 0, FIFO_READ_STATE = 1, TX_STATE = 2, END_STATE = 3;
	
	always @ (posedge clk_i or negedge rst_n_i)begin
		if(rst_n_i == 0)begin
			state <= IDLE_STATE;
			txd_r <= 1;
			fifo_rd_r <= 0;
			tx_cnt <= 0;
			tx_buf_r <= 0;
		end else begin
			case(state)
				IDLE_STATE:begin
					txd_r <= 1;
					tx_cnt <= 0;
					if(!fifo_empty_i)begin
						fifo_rd_r <= 1;
						state <= FIFO_READ_STATE;
					end
				end
				FIFO_READ_STATE:begin
					fifo_rd_r <= 0;
					tx_buf_r <= {1'b0, fifo_data_i,1'b1}; //start bit, data , stop bit
					state <= TX_STATE;
				end
				TX_STATE:begin
					if(tx_timing_i)begin
						txd_r <= tx_buf_r[9];
						tx_buf_r[9:0] <= {tx_buf_r[8:0], 1'b0};
						tx_cnt <= tx_cnt + 1;
						if(tx_cnt == 9)begin
							state <= END_STATE;
						end 
					end
				end
			 END_STATE:begin
				 state <= IDLE_STATE;
			 end
			endcase // case(state)
		end
	end					 

	assign fifo_rd_o = fifo_rd_r;
	assign txd_o = txd_r;

endmodule // nuart_tx

measure/cam2disp_measure/cores/uart_t/rtl/nuart_rx.v
module nuart_rx(clk_i, x16clk_i, rst_n_i, fifo_wr_o, fifo_data_o, rxd_i);
	input clk_i; 
	input x16clk_i; //x16 clock for RS232C
	input rst_n_i; 
	output fifo_wr_o; 
	output [7:0] fifo_data_o; 
	input rxd_i;

	reg [1:0] rxd_r;
	wire 			rxd_fall;

	reg [3:0] x16cnt_r;
	reg 			sampling_timing_r;
	reg 			fifo_wr_r;
	reg [7:0] rx_buf_r;
	
	reg [3:0] state;
	parameter IDLE_STATE = 0, START_BIT_STATE = 1, RX_STATE = 2, FIFO_WR_STATE = 3, END_STATE = 4;
	wire 			rx_in;
	reg [3:0] rx_cnt_r;
	
	always @ (posedge clk_i or negedge rst_n_i)begin
		if(rst_n_i == 0)begin
			fifo_wr_r <= 0;
			state <= IDLE_STATE;
		end else begin
			case(state)
				IDLE_STATE:begin
					fifo_wr_r <= 0;
					rx_buf_r <= 0;
					rx_cnt_r <= 0;
					if(rxd_fall)begin
						state <= START_BIT_STATE;
					end
				end
				START_BIT_STATE:begin
					if(sampling_timing_r)begin
						if(rx_in)begin  // no start bit
							state <= IDLE_STATE;
						end else begin
							state <= RX_STATE;
						end
					end
				end
				RX_STATE:begin
					if(sampling_timing_r)begin
						rx_buf_r <= {rx_buf_r[6:0], rx_in};
						rx_cnt_r <= rx_cnt_r + 1;
						if(rx_cnt_r == 7)begin
							state <= FIFO_WR_STATE;
						end
					end
				end
				FIFO_WR_STATE:begin
					fifo_wr_r <= 1;
					state <= END_STATE;
				end
				END_STATE:begin
					fifo_wr_r <= 0;
					state <= IDLE_STATE;
				end
			endcase // case(state)
		end
	end


	// fall detect
	assign 		rxd_fall = rxd_r[1] & !rxd_r[0];
	assign 		rx_in = rxd_r[1];
	always @ (posedge clk_i or negedge rst_n_i)begin
		if(rst_n_i == 0)begin
			rxd_r <= 2'b11;
		end else begin
			rxd_r <= {rxd_r[0], rxd_i};
		end
	end

	//adjust sampling timing
	always @ (posedge clk_i or negedge rst_n_i)begin
		if(rst_n_i == 0)begin
			x16cnt_r <= 0;
		end else begin
			if((state == IDLE_STATE) && rxd_fall)begin
				x16cnt_r <= 8;  // adjust
			end else if(x16clk_i)begin
				x16cnt_r <= x16cnt_r + 1;  // expect overflow
			end
		end
	end

	always @ (posedge clk_i or negedge rst_n_i)begin
		if(rst_n_i == 0)begin
			sampling_timing_r <= 0;
		end else begin
			sampling_timing_r <= (x16clk_i && x16cnt_r == 0) ? 1 : 0;
		end
	end

	assign fifo_data_o = rx_buf_r;
	assign fifo_wr_o = fifo_wr_r;
	
endmodule

measure/cam2disp_measure/cores/uart_t/rtl/nuart_clkgen.v
module nuart_clkgen(clk_i, rst_n_i, tx_timing_o, rx_timing_x16_o);
	input clk_i;
	input rst_n_i;
	output tx_timing_o;
	output rx_timing_x16_o;

	parameter X16CLK_DIVINE_NUMBER = 50;

	reg [31:0] counter_r;
	reg [3:0]  x16_counter_r;
	reg 			 overflow_r;
	reg 			 tx_timing_r;
	
	always @ (posedge clk_i or negedge rst_n_i)begin
		if(rst_n_i == 0)begin
			counter_r <= 0;
		end else begin
			if(counter_r == X16CLK_DIVINE_NUMBER - 1)begin
				counter_r <= 0;
			end else begin
				counter_r <= counter_r + 1;
			end
		end
	end
	
	always @ (posedge clk_i or negedge rst_n_i)begin
		if(rst_n_i == 0)begin
			overflow_r <= 0;
		end else begin
			overflow_r <= (counter_r == 0) ? 1 : 0;
		end
	end
	
	always @ (posedge clk_i or negedge rst_n_i)begin
		if(rst_n_i == 0)begin
			x16_counter_r <= 0;
		end else begin
			if(overflow_r)begin
				x16_counter_r <= x16_counter_r + 1;
			end
		end
	end
	
	always @ (posedge clk_i or negedge rst_n_i)begin
		if(rst_n_i == 0)begin
			tx_timing_r <= 0;
		end else begin
			if(overflow_r & (x16_counter_r == 0))begin
				tx_timing_r <= 1;
			end else begin
				tx_timing_r <= 0;
			end
		end
	end
	
	assign rx_timing_x16_o = overflow_r;
	assign tx_timing_o = tx_timing_r;

endmodule // uart_clkgen

measure/cam2disp_measure/cores/uart_t/rtl/nuart.v
module nuart(clk_i, rst_n_i, Txd_o, Rxd_i, 
						 tx_fifo_rd_o, tx_fifo_data_i, tx_fifo_empty_i,
						 rx_fifo_wr_o, rx_fifo_data_o);
	
	input clk_i; // clk
	input rst_n_i; // asynchronous reset, low active

	//RS 232-C interface
	output Txd_o;  // RS 232-C tx data
	input  Rxd_i;  // RS 233-C rx data

	//tx fifo interface
	output tx_fifo_rd_o;  // tx fifo read request
	input [7:0] tx_fifo_data_i; // tx fifo read data
	input 			tx_fifo_empty_i; // tx fifo empty 

	//rx fifo interface 
	output 			rx_fifo_wr_o;  // rx fifo write request
	output [7:0] rx_fifo_data_o; // rx fifo data

	parameter X16CLK_DIVINE_NUMBER = 50;

	wire 			clk;
	wire 			rst_n;
	wire 			tx_timing;
	wire 			x16_timing;

	
	assign 		clk = clk_i;
	assign    rst_n = rst_n_i;

	defparam 	clkgen.X16CLK_DIVINE_NUMBER = X16CLK_DIVINE_NUMBER;
	nuart_clkgen clkgen 
		(
		 .clk_i(clk),
		 .rst_n_i(rst_n),
		 .tx_timing_o(tx_timing),
		 .rx_timing_x16_o(x16_timing)
		 );
	
	
	nuart_rx rx
		(
		 .clk_i(clk),
		 .x16clk_i(x16_timing),
		 .rst_n_i(rst_n),
		 .fifo_wr_o(rx_fifo_wr_o),
		 .fifo_data_o(rx_fifo_data_o),
		 .rxd_i(Rxd_i)
		 );

	nuart_tx tx
		(
		 .clk_i(clk),
		 .rst_n_i(rst_n),
		 .tx_timing_i(tx_timing),
		 .txd_o(Txd_o),
		 .fifo_rd_o(tx_fifo_rd_o),
		 .fifo_data_i(tx_fifo_data_i),
		 .fifo_empty_i(tx_fifo_empty_i)
		 );
	
	

endmodule // unart

measure/cam2disp_measure/cores/uart_t/test/tb_uart.v
`timescale 1ns / 1ps

`define simulation

module tb_uart();


//
// System Clock 50MHz
//
reg sys_clk;
initial sys_clk = 1'b0;
always #10 sys_clk = ~sys_clk;



//
// Test Bench
//
reg sys_rst;
wire TX,RX;
assign RX = 1'b1;
wire [7:0]data = 8'd49;
reg empty;
wire req;

nuart u0 (
  .clk_i(sys_clk), 
	.rst_n_i(sys_rst), 
	.Txd_o(TX), 
	.Rxd_i(RX), 
	.tx_fifo_rd_o(req),
	.tx_fifo_data_i(data), 
	.tx_fifo_empty_i(empty),
	.rx_fifo_wr_o(), 
	.rx_fifo_data_o()
);

//
// a clock
//
task waitclock;
begin
	@(posedge sys_clk);
	#1;
end
endtask

//
// Scinario
//


initial begin
	$dumpfile("./test.vcd");
	$dumpvars(0, tb_uart);
	sys_rst = 1'b0;
	empty  = 0;
	
	waitclock;
	waitclock;
	
	sys_rst = 1'b1;
	
	waitclock;
	
  #100;
	empty = 1'b1;
  #1;
	empty = 1'b0;
	#1;
	empty = 1'b1;
	
	#200000;
	$finish;
end

endmodule

measure/cam2disp_measure/cores/uart_t/test/test.vcd
$date
	Thu Jun 19 17:27:39 2014
$end
$version
	Icarus Verilog
$end
$timescale
	1ps
$end
$scope module tb_uart $end
$var wire 1 ! RX $end
$var wire 1 " TX $end
$var wire 8 # data [7:0] $end
$var wire 1 $ req $end
$var reg 1 % empty $end
$var reg 1 & sys_clk $end
$var reg 1 ' sys_rst $end
$scope module u0 $end
$var wire 1 ! Rxd_i $end
$var wire 1 " Txd_o $end
$var wire 1 ( clk $end
$var wire 1 ) clk_i $end
$var wire 1 * rst_n $end
$var wire 1 + rst_n_i $end
$var wire 8 , rx_fifo_data_o [7:0] $end
$var wire 1 - rx_fifo_wr_o $end
$var wire 8 . tx_fifo_data_i [7:0] $end
$var wire 1 / tx_fifo_empty_i $end
$var wire 1 $ tx_fifo_rd_o $end
$var wire 1 0 tx_timing $end
$var wire 1 1 x16_timing $end
$scope module clkgen $end
$var wire 1 ( clk_i $end
$var wire 1 * rst_n_i $end
$var wire 1 1 rx_timing_x16_o $end
$var wire 1 0 tx_timing_o $end
$var reg 32 2 counter_r [31:0] $end
$var reg 1 3 overflow_r $end
$var reg 1 4 tx_timing_r $end
$var reg 4 5 x16_counter_r [3:0] $end
$upscope $end
$scope module rx $end
$var wire 1 ( clk_i $end
$var wire 8 6 fifo_data_o [7:0] $end
$var wire 1 - fifo_wr_o $end
$var wire 1 * rst_n_i $end
$var wire 1 7 rx_in $end
$var wire 1 8 rxd_fall $end
$var wire 1 ! rxd_i $end
$var wire 1 1 x16clk_i $end
$var reg 1 9 fifo_wr_r $end
$var reg 8 : rx_buf_r [7:0] $end
$var reg 4 ; rx_cnt_r [3:0] $end
$var reg 2 < rxd_r [1:0] $end
$var reg 1 = sampling_timing_r $end
$var reg 4 > state [3:0] $end
$var reg 4 ? x16cnt_r [3:0] $end
$upscope $end
$scope module tx $end
$var wire 1 ( clk_i $end
$var wire 8 @ fifo_data_i [7:0] $end
$var wire 1 / fifo_empty_i $end
$var wire 1 $ fifo_rd_o $end
$var wire 1 * rst_n_i $end
$var wire 1 0 tx_timing_i $end
$var wire 1 " txd_o $end
$var reg 1 A fifo_rd_r $end
$var reg 4 B state [3:0] $end
$var reg 10 C tx_buf_r [9:0] $end
$var reg 4 D tx_cnt [3:0] $end
$var reg 1 E txd_r $end
$upscope $end
$upscope $end
$scope task waitclock $end
$upscope $end
$upscope $end
$enddefinitions $end
#0
$dumpvars
1E
b0 D
b0 C
b0 B
0A
b110001 @
b0 ?
b0 >
0=
b11 <
bx ;
bx :
09
08
17
bx 6
b0 5
04
03
b0 2
01
00
0/
b110001 .
0-
bx ,
0+
0*
0)
0(
0'
0&
0%
0$
b110001 #
1"
1!
$end
#10000
1&
1(
1)
#20000
0&
0(
0)
#30000
1&
1(
1)
#31000
1'
1*
1+
#40000
0&
0(
0)
#50000
b1 B
1A
1$
b0 ;
b0 :
b0 ,
b0 6
13
11
b1 2
1&
1(
1)
#60000
0&
0(
0)
#70000
b10 2
03
01
b1 5
14
10
b1 ?
1=
b10 B
b1100011 C
0A
0$
1&
1(
1)
#80000
0&
0(
0)
#90000
b1 D
b11000110 C
0E
0"
0=
04
00
b11 2
1&
1(
1)
#100000
0&
0(
0)
#110000
b100 2
1&
1(
1)
#120000
0&
0(
0)
#130000
b101 2
1&
1(
1)
#140000
0&
0(
0)
#150000
b110 2
1&
1(
1)
#151000
1%
1/
#152000
0%
0/
#153000
1%
1/
#160000
0&
0(
0)
#170000
b111 2
1&
1(
1)
#180000
0&
0(
0)
#190000
b1000 2
1&
1(
1)
#200000
0&
0(
0)
#210000
b1001 2
1&
1(
1)
#220000
0&
0(
0)
#230000
b1010 2
1&
1(
1)
#240000
0&
0(
0)
#250000
b1011 2
1&
1(
1)
#260000
0&
0(
0)
#270000
b1100 2
1&
1(
1)
#280000
0&
0(
0)
#290000
b1101 2
1&
1(
1)
#300000
0&
0(
0)
#310000
b1110 2
1&
1(
1)
#320000
0&
0(
0)
#330000
b1111 2
1&
1(
1)
#340000
0&
0(
0)
#350000
b10000 2
1&
1(
1)
#360000
0&
0(
0)
#370000
b10001 2
1&
1(
1)
#380000
0&
0(
0)
#390000
b10010 2
1&
1(
1)
#400000
0&
0(
0)
#410000
b10011 2
1&
1(
1)
#420000
0&
0(
0)
#430000
b10100 2
1&
1(
1)
#440000
0&
0(
0)
#450000
b10101 2
1&
1(
1)
#460000
0&
0(
0)
#470000
b10110 2
1&
1(
1)
#480000
0&
0(
0)
#490000
b10111 2
1&
1(
1)
#500000
0&
0(
0)
#510000
b11000 2
1&
1(
1)
#520000
0&
0(
0)
#530000
b11001 2
1&
1(
1)
#540000
0&
0(
0)
#550000
b11010 2
1&
1(
1)
#560000
0&
0(
0)
#570000
b11011 2
1&
1(
1)
#580000
0&
0(
0)
#590000
b11100 2
1&
1(
1)
#600000
0&
0(
0)
#610000
b11101 2
1&
1(
1)
#620000
0&
0(
0)
#630000
b11110 2
1&
1(
1)
#640000
0&
0(
0)
#650000
b11111 2
1&
1(
1)
#660000
0&
0(
0)
#670000
b100000 2
1&
1(
1)
#680000
0&
0(
0)
#690000
b100001 2
1&
1(
1)
#700000
0&
0(
0)
#710000
b100010 2
1&
1(
1)
#720000
0&
0(
0)
#730000
b100011 2
1&
1(
1)
#740000
0&
0(
0)
#750000
b100100 2
1&
1(
1)
#760000
0&
0(
0)
#770000
b100101 2
1&
1(
1)
#780000
0&
0(
0)
#790000
b100110 2
1&
1(
1)
#800000
0&
0(
0)
#810000
b100111 2
1&
1(
1)
#820000
0&
0(
0)
#830000
b101000 2
1&
1(
1)
#840000
0&
0(
0)
#850000
b101001 2
1&
1(
1)
#860000
0&
0(
0)
#870000
b101010 2
1&
1(
1)
#880000
0&
0(
0)
#890000
b101011 2
1&
1(
1)
#900000
0&
0(
0)
#910000
b101100 2
1&
1(
1)
#920000
0&
0(
0)
#930000
b101101 2
1&
1(
1)
#940000
0&
0(
0)
#950000
b101110 2
1&
1(
1)
#960000
0&
0(
0)
#970000
b101111 2
1&
1(
1)
#980000
0&
0(
0)
#990000
b110000 2
1&
1(
1)
#1000000
0&
0(
0)
#1010000
b110001 2
1&
1(
1)
#1020000
0&
0(
0)
#1030000
b0 2
1&
1(
1)
#1040000
0&
0(
0)
#1050000
13
11
b1 2
1&
1(
1)
#1060000
0&
0(
0)
#1070000
b10 2
03
01
b10 5
b10 ?
1&
1(
1)
#1080000
0&
0(
0)
#1090000
b11 2
1&
1(
1)
#1100000
0&
0(
0)
#1110000
b100 2
1&
1(
1)
#1120000
0&
0(
0)
#1130000
b101 2
1&
1(
1)
#1140000
0&
0(
0)
#1150000
b110 2
1&
1(
1)
#1160000
0&
0(
0)
#1170000
b111 2
1&
1(
1)
#1180000
0&
0(
0)
#1190000
b1000 2
1&
1(
1)
#1200000
0&
0(
0)
#1210000
b1001 2
1&
1(
1)
#1220000
0&
0(
0)
#1230000
b1010 2
1&
1(
1)
#1240000
0&
0(
0)
#1250000
b1011 2
1&
1(
1)
#1260000
0&
0(
0)
#1270000
b1100 2
1&
1(
1)
#1280000
0&
0(
0)
#1290000
b1101 2
1&
1(
1)
#1300000
0&
0(
0)
#1310000
b1110 2
1&
1(
1)
#1320000
0&
0(
0)
#1330000
b1111 2
1&
1(
1)
#1340000
0&
0(
0)
#1350000
b10000 2
1&
1(
1)
#1360000
0&
0(
0)
#1370000
b10001 2
1&
1(
1)
#1380000
0&
0(
0)
#1390000
b10010 2
1&
1(
1)
#1400000
0&
0(
0)
#1410000
b10011 2
1&
1(
1)
#1420000
0&
0(
0)
#1430000
b10100 2
1&
1(
1)
#1440000
0&
0(
0)
#1450000
b10101 2
1&
1(
1)
#1460000
0&
0(
0)
#1470000
b10110 2
1&
1(
1)
#1480000
0&
0(
0)
#1490000
b10111 2
1&
1(
1)
#1500000
0&
0(
0)
#1510000
b11000 2
1&
1(
1)
#1520000
0&
0(
0)
#1530000
b11001 2
1&
1(
1)
#1540000
0&
0(
0)
#1550000
b11010 2
1&
1(
1)
#1560000
0&
0(
0)
#1570000
b11011 2
1&
1(
1)
#1580000
0&
0(
0)
#1590000
b11100 2
1&
1(
1)
#1600000
0&
0(
0)
#1610000
b11101 2
1&
1(
1)
#1620000
0&
0(
0)
#1630000
b11110 2
1&
1(
1)
#1640000
0&
0(
0)
#1650000
b11111 2
1&
1(
1)
#1660000
0&
0(
0)
#1670000
b100000 2
1&
1(
1)
#1680000
0&
0(
0)
#1690000
b100001 2
1&
1(
1)
#1700000
0&
0(
0)
#1710000
b100010 2
1&
1(
1)
#1720000
0&
0(
0)
#1730000
b100011 2
1&
1(
1)
#1740000
0&
0(
0)
#1750000
b100100 2
1&
1(
1)
#1760000
0&
0(
0)
#1770000
b100101 2
1&
1(
1)
#1780000
0&
0(
0)
#1790000
b100110 2
1&
1(
1)
#1800000
0&
0(
0)
#1810000
b100111 2
1&
1(
1)
#1820000
0&
0(
0)
#1830000
b101000 2
1&
1(
1)
#1840000
0&
0(
0)
#1850000
b101001 2
1&
1(
1)
#1860000
0&
0(
0)
#1870000
b101010 2
1&
1(
1)
#1880000
0&
0(
0)
#1890000
b101011 2
1&
1(
1)
#1900000
0&
0(
0)
#1910000
b101100 2
1&
1(
1)
#1920000
0&
0(
0)
#1930000
b101101 2
1&
1(
1)
#1940000
0&
0(
0)
#1950000
b101110 2
1&
1(
1)
#1960000
0&
0(
0)
#1970000
b101111 2
1&
1(
1)
#1980000
0&
0(
0)
#1990000
b110000 2
1&
1(
1)
#2000000
0&
0(
0)
#2010000
b110001 2
1&
1(
1)
#2020000
0&
0(
0)
#2030000
b0 2
1&
1(
1)
#2040000
0&
0(
0)
#2050000
13
11
b1 2
1&
1(
1)
#2060000
0&
0(
0)
#2070000
b10 2
03
01
b11 5
b11 ?
1&
1(
1)
#2080000
0&
0(
0)
#2090000
b11 2
1&
1(
1)
#2100000
0&
0(
0)
#2110000
b100 2
1&
1(
1)
#2120000
0&
0(
0)
#2130000
b101 2
1&
1(
1)
#2140000
0&
0(
0)
#2150000
b110 2
1&
1(
1)
#2160000
0&
0(
0)
#2170000
b111 2
1&
1(
1)
#2180000
0&
0(
0)
#2190000
b1000 2
1&
1(
1)
#2200000
0&
0(
0)
#2210000
b1001 2
1&
1(
1)
#2220000
0&
0(
0)
#2230000
b1010 2
1&
1(
1)
#2240000
0&
0(
0)
#2250000
b1011 2
1&
1(
1)
#2260000
0&
0(
0)
#2270000
b1100 2
1&
1(
1)
#2280000
0&
0(
0)
#2290000
b1101 2
1&
1(
1)
#2300000
0&
0(
0)
#2310000
b1110 2
1&
1(
1)
#2320000
0&
0(
0)
#2330000
b1111 2
1&
1(
1)
#2340000
0&
0(
0)
#2350000
b10000 2
1&
1(
1)
#2360000
0&
0(
0)
#2370000
b10001 2
1&
1(
1)
#2380000
0&
0(
0)
#2390000
b10010 2
1&
1(
1)
#2400000
0&
0(
0)
#2410000
b10011 2
1&
1(
1)
#2420000
0&
0(
0)
#2430000
b10100 2
1&
1(
1)
#2440000
0&
0(
0)
#2450000
b10101 2
1&
1(
1)
#2460000
0&
0(
0)
#2470000
b10110 2
1&
1(
1)
#2480000
0&
0(
0)
#2490000
b10111 2
1&
1(
1)
#2500000
0&
0(
0)
#2510000
b11000 2
1&
1(
1)
#2520000
0&
0(
0)
#2530000
b11001 2
1&
1(
1)
#2540000
0&
0(
0)
#2550000
b11010 2
1&
1(
1)
#2560000
0&
0(
0)
#2570000
b11011 2
1&
1(
1)
#2580000
0&
0(
0)
#2590000
b11100 2
1&
1(
1)
#2600000
0&
0(
0)
#2610000
b11101 2
1&
1(
1)
#2620000
0&
0(
0)
#2630000
b11110 2
1&
1(
1)
#2640000
0&
0(
0)
#2650000
b11111 2
1&
1(
1)
#2660000
0&
0(
0)
#2670000
b100000 2
1&
1(
1)
#2680000
0&
0(
0)
#2690000
b100001 2
1&
1(
1)
#2700000
0&
0(
0)
#2710000
b100010 2
1&
1(
1)
#2720000
0&
0(
0)
#2730000
b100011 2
1&
1(
1)
#2740000
0&
0(
0)
#2750000
b100100 2
1&
1(
1)
#2760000
0&
0(
0)
#2770000
b100101 2
1&
1(
1)
#2780000
0&
0(
0)
#2790000
b100110 2
1&
1(
1)
#2800000
0&
0(
0)
#2810000
b100111 2
1&
1(
1)
#2820000
0&
0(
0)
#2830000
b101000 2
1&
1(
1)
#2840000
0&
0(
0)
#2850000
b101001 2
1&
1(
1)
#2860000
0&
0(
0)
#2870000
b101010 2
1&
1(
1)
#2880000
0&
0(
0)
#2890000
b101011 2
1&
1(
1)
#2900000
0&
0(
0)
#2910000
b101100 2
1&
1(
1)
#2920000
0&
0(
0)
#2930000
b101101 2
1&
1(
1)
#2940000
0&
0(
0)
#2950000
b101110 2
1&
1(
1)
#2960000
0&
0(
0)
#2970000
b101111 2
1&
1(
1)
#2980000
0&
0(
0)
#2990000
b110000 2
1&
1(
1)
#3000000
0&
0(
0)
#3010000
b110001 2
1&
1(
1)
#3020000
0&
0(
0)
#3030000
b0 2
1&
1(
1)
#3040000
0&
0(
0)
#3050000
13
11
b1 2
1&
1(
1)
#3060000
0&
0(
0)
#3070000
b10 2
03
01
b100 5
b100 ?
1&
1(
1)
#3080000
0&
0(
0)
#3090000
b11 2
1&
1(
1)
#3100000
0&
0(
0)
#3110000
b100 2
1&
1(
1)
#3120000
0&
0(
0)
#3130000
b101 2
1&
1(
1)
#3140000
0&
0(
0)
#3150000
b110 2
1&
1(
1)
#3160000
0&
0(
0)
#3170000
b111 2
1&
1(
1)
#3180000
0&
0(
0)
#3190000
b1000 2
1&
1(
1)
#3200000
0&
0(
0)
#3210000
b1001 2
1&
1(
1)
#3220000
0&
0(
0)
#3230000
b1010 2
1&
1(
1)
#3240000
0&
0(
0)
#3250000
b1011 2
1&
1(
1)
#3260000
0&
0(
0)
#3270000
b1100 2
1&
1(
1)
#3280000
0&
0(
0)
#3290000
b1101 2
1&
1(
1)
#3300000
0&
0(
0)
#3310000
b1110 2
1&
1(
1)
#3320000
0&
0(
0)
#3330000
b1111 2
1&
1(
1)
#3340000
0&
0(
0)
#3350000
b10000 2
1&
1(
1)
#3360000
0&
0(
0)
#3370000
b10001 2
1&
1(
1)
#3380000
0&
0(
0)
#3390000
b10010 2
1&
1(
1)
#3400000
0&
0(
0)
#3410000
b10011 2
1&
1(
1)
#3420000
0&
0(
0)
#3430000
b10100 2
1&
1(
1)
#3440000
0&
0(
0)
#3450000
b10101 2
1&
1(
1)
#3460000
0&
0(
0)
#3470000
b10110 2
1&
1(
1)
#3480000
0&
0(
0)
#3490000
b10111 2
1&
1(
1)
#3500000
0&
0(
0)
#3510000
b11000 2
1&
1(
1)
#3520000
0&
0(
0)
#3530000
b11001 2
1&
1(
1)
#3540000
0&
0(
0)
#3550000
b11010 2
1&
1(
1)
#3560000
0&
0(
0)
#3570000
b11011 2
1&
1(
1)
#3580000
0&
0(
0)
#3590000
b11100 2
1&
1(
1)
#3600000
0&
0(
0)
#3610000
b11101 2
1&
1(
1)
#3620000
0&
0(
0)
#3630000
b11110 2
1&
1(
1)
#3640000
0&
0(
0)
#3650000
b11111 2
1&
1(
1)
#3660000
0&
0(
0)
#3670000
b100000 2
1&
1(
1)
#3680000
0&
0(
0)
#3690000
b100001 2
1&
1(
1)
#3700000
0&
0(
0)
#3710000
b100010 2
1&
1(
1)
#3720000
0&
0(
0)
#3730000
b100011 2
1&
1(
1)
#3740000
0&
0(
0)
#3750000
b100100 2
1&
1(
1)
#3760000
0&
0(
0)
#3770000
b100101 2
1&
1(
1)
#3780000
0&
0(
0)
#3790000
b100110 2
1&
1(
1)
#3800000
0&
0(
0)
#3810000
b100111 2
1&
1(
1)
#3820000
0&
0(
0)
#3830000
b101000 2
1&
1(
1)
#3840000
0&
0(
0)
#3850000
b101001 2
1&
1(
1)
#3860000
0&
0(
0)
#3870000
b101010 2
1&
1(
1)
#3880000
0&
0(
0)
#3890000
b101011 2
1&
1(
1)
#3900000
0&
0(
0)
#3910000
b101100 2
1&
1(
1)
#3920000
0&
0(
0)
#3930000
b101101 2
1&
1(
1)
#3940000
0&
0(
0)
#3950000
b101110 2
1&
1(
1)
#3960000
0&
0(
0)
#3970000
b101111 2
1&
1(
1)
#3980000
0&
0(
0)
#3990000
b110000 2
1&
1(
1)
#4000000
0&
0(
0)
#4010000
b110001 2
1&
1(
1)
#4020000
0&
0(
0)
#4030000
b0 2
1&
1(
1)
#4040000
0&
0(
0)
#4050000
13
11
b1 2
1&
1(
1)
#4060000
0&
0(
0)
#4070000
b10 2
03
01
b101 5
b101 ?
1&
1(
1)
#4080000
0&
0(
0)
#4090000
b11 2
1&
1(
1)
#4100000
0&
0(
0)
#4110000
b100 2
1&
1(
1)
#4120000
0&
0(
0)
#4130000
b101 2
1&
1(
1)
#4140000
0&
0(
0)
#4150000
b110 2
1&
1(
1)
#4160000
0&
0(
0)
#4170000
b111 2
1&
1(
1)
#4180000
0&
0(
0)
#4190000
b1000 2
1&
1(
1)
#4200000
0&
0(
0)
#4210000
b1001 2
1&
1(
1)
#4220000
0&
0(
0)
#4230000
b1010 2
1&
1(
1)
#4240000
0&
0(
0)
#4250000
b1011 2
1&
1(
1)
#4260000
0&
0(
0)
#4270000
b1100 2
1&
1(
1)
#4280000
0&
0(
0)
#4290000
b1101 2
1&
1(
1)
#4300000
0&
0(
0)
#4310000
b1110 2
1&
1(
1)
#4320000
0&
0(
0)
#4330000
b1111 2
1&
1(
1)
#4340000
0&
0(
0)
#4350000
b10000 2
1&
1(
1)
#4360000
0&
0(
0)
#4370000
b10001 2
1&
1(
1)
#4380000
0&
0(
0)
#4390000
b10010 2
1&
1(
1)
#4400000
0&
0(
0)
#4410000
b10011 2
1&
1(
1)
#4420000
0&
0(
0)
#4430000
b10100 2
1&
1(
1)
#4440000
0&
0(
0)
#4450000
b10101 2
1&
1(
1)
#4460000
0&
0(
0)
#4470000
b10110 2
1&
1(
1)
#4480000
0&
0(
0)
#4490000
b10111 2
1&
1(
1)
#4500000
0&
0(
0)
#4510000
b11000 2
1&
1(
1)
#4520000
0&
0(
0)
#4530000
b11001 2
1&
1(
1)
#4540000
0&
0(
0)
#4550000
b11010 2
1&
1(
1)
#4560000
0&
0(
0)
#4570000
b11011 2
1&
1(
1)
#4580000
0&
0(
0)
#4590000
b11100 2
1&
1(
1)
#4600000
0&
0(
0)
#4610000
b11101 2
1&
1(
1)
#4620000
0&
0(
0)
#4630000
b11110 2
1&
1(
1)
#4640000
0&
0(
0)
#4650000
b11111 2
1&
1(
1)
#4660000
0&
0(
0)
#4670000
b100000 2
1&
1(
1)
#4680000
0&
0(
0)
#4690000
b100001 2
1&
1(
1)
#4700000
0&
0(
0)
#4710000
b100010 2
1&
1(
1)
#4720000
0&
0(
0)
#4730000
b100011 2
1&
1(
1)
#4740000
0&
0(
0)
#4750000
b100100 2
1&
1(
1)
#4760000
0&
0(
0)
#4770000
b100101 2
1&
1(
1)
#4780000
0&
0(
0)
#4790000
b100110 2
1&
1(
1)
#4800000
0&
0(
0)
#4810000
b100111 2
1&
1(
1)
#4820000
0&
0(
0)
#4830000
b101000 2
1&
1(
1)
#4840000
0&
0(
0)
#4850000
b101001 2
1&
1(
1)
#4860000
0&
0(
0)
#4870000
b101010 2
1&
1(
1)
#4880000
0&
0(
0)
#4890000
b101011 2
1&
1(
1)
#4900000
0&
0(
0)
#4910000
b101100 2
1&
1(
1)
#4920000
0&
0(
0)
#4930000
b101101 2
1&
1(
1)
#4940000
0&
0(
0)
#4950000
b101110 2
1&
1(
1)
#4960000
0&
0(
0)
#4970000
b101111 2
1&
1(
1)
#4980000
0&
0(
0)
#4990000
b110000 2
1&
1(
1)
#5000000
0&
0(
0)
#5010000
b110001 2
1&
1(
1)
#5020000
0&
0(
0)
#5030000
b0 2
1&
1(
1)
#5040000
0&
0(
0)
#5050000
13
11
b1 2
1&
1(
1)
#5060000
0&
0(
0)
#5070000
b10 2
03
01
b110 5
b110 ?
1&
1(
1)
#5080000
0&
0(
0)
#5090000
b11 2
1&
1(
1)
#5100000
0&
0(
0)
#5110000
b100 2
1&
1(
1)
#5120000
0&
0(
0)
#5130000
b101 2
1&
1(
1)
#5140000
0&
0(
0)
#5150000
b110 2
1&
1(
1)
#5160000
0&
0(
0)
#5170000
b111 2
1&
1(
1)
#5180000
0&
0(
0)
#5190000
b1000 2
1&
1(
1)
#5200000
0&
0(
0)
#5210000
b1001 2
1&
1(
1)
#5220000
0&
0(
0)
#5230000
b1010 2
1&
1(
1)
#5240000
0&
0(
0)
#5250000
b1011 2
1&
1(
1)
#5260000
0&
0(
0)
#5270000
b1100 2
1&
1(
1)
#5280000
0&
0(
0)
#5290000
b1101 2
1&
1(
1)
#5300000
0&
0(
0)
#5310000
b1110 2
1&
1(
1)
#5320000
0&
0(
0)
#5330000
b1111 2
1&
1(
1)
#5340000
0&
0(
0)
#5350000
b10000 2
1&
1(
1)
#5360000
0&
0(
0)
#5370000
b10001 2
1&
1(
1)
#5380000
0&
0(
0)
