display_measure/cores/uart/uart_tx.v
module uart_tx()
  input  wire clk,
	input  wire rst,
	input  wire [7:0] data,
	input  wire we,
	output reg  tx,
	output reg  wr
);

 reg [3:0] cnt;
 reg dclk;
 always @ (posedge clk)begin
	 if(rst)begin
		 cnt16 <= 4'd0;
		 dclk  <= 1'b0;
	 end else begin
	   if(cnt == 4'd15)begin
			 cnt  <= 4'd0;
			 dclk <= ~dclk;
		 end else
			 cnt <= cnt + 4'd1;
   end
 end
	 
 /* FSM */
 reg [1:0]state;
 reg [7:0] sfd;
 reg [2:0]dcnt;

 parameter IDLE  = 2'b00;
 parameter START = 2'b01;
 parameter DATA  = 2'b10;
 parameter STOP  = 2'b11;

 always @ (posedge dclk) begin
   if(rst) begin
		 wr    <= 1'b0;
		 tx    <= 1'b0;
		 state <= 2'd0;
		 sfd   <= 8'd0;
		 dcnt  <= 3'd0;
	 end else begin
		 case(state)
		   IDLE  : begin
                 tx   <= 1'b1;
								 dcnt <= 3'd0;
								 wr   <= 1'b0;
								 if(we)begin
									 state <= START;
									 sfd   <= data;
								 end
               end
			 START : begin
                 tx    <= 1'b0;
								 dcnt  <= 3'd0;
								 state <= DATA;
								 wr    <= 1'b1;
               end
			 DATA  : begin
                 tx <= sfd[0]; 
                 sfd <= {1'b0, sfd[7:1]};
								 if(dcnt == 3'd7)
									 state <= DATA;
								 else
									 dcnt <= dcnt + 3'd1;
							 end
			 STOP  : begin
                 tx <= 1'b1;
								 state <= IDLE;
								 wr <= 1'b0;
               end
     endcase
 end

endmodule

measure/hdmi_measure/cores/uart/test/tb_uart.v
`timescale 1ns / 1ps

module tb_uart();

//
// System Clock 125MHz
//
reg sys_clk;
initial sys_clk = 1'b0;
always #8 sys_clk = ~sys_clk;

reg sys_rst;

reg [7:0] d;
reg we;

wire txd;
wire err;

uart_tx u0(
  .clk(sys_clk),
	.rst(sys_rst),
	.data(d),
	.we(we),
	.tx(txd),
	.wr(err)
);

//
// a clock
//
task waitclock;
begin
	@(posedge sys_clk);
	#1;
end
endtask

reg [7:0] mem [7:0]


//
// Scinario
//
initial begin
	$dumpfile("./test.vcd");
	$dumpvars(0, tb_uart);
	sys_rst = 1'b1;

	waitclock;
	waitclock;

	sys_rst = 1'b0;

	waitclock;
  
  if(~err)begin
    d <= 8'd0; 
    we <= 1;
    #1;
  end
  
  if(~err)begin
    d <= 8'd40; 
    we <= 1;
    #1;
  end
  
  if(~err)begin
    d <= 8'd90; 
    we <= 1;
    #1;
  end

	#100000;
	$finish;
end

endmodule

measure/display_measure/cores/uart/test/test.vcd
$date
	Fri May 30 03:07:42 2014
$end
$version
	Icarus Verilog
$end
$timescale
	1ps
$end
$scope module tb_uart $end
$var wire 1 ! err $end
$var wire 1 " txd $end
$var reg 8 # d [7:0] $end
$var reg 1 $ sys_clk $end
$var reg 1 % sys_rst $end
$var reg 1 & we $end
$scope module u0 $end
$var wire 1 ' clk $end
$var wire 8 ( data [7:0] $end
$var wire 1 ) rst $end
$var wire 1 * we $end
$var reg 4 + cnt [3:0] $end
$var reg 1 , dclk $end
$var reg 3 - dcnt [2:0] $end
$var reg 8 . sfd [7:0] $end
$var reg 2 / state [1:0] $end
$var reg 1 0 tx $end
$var reg 1 1 wr $end
$upscope $end
$scope task waitclock $end
$upscope $end
$upscope $end
$enddefinitions $end
#0
$dumpvars
01
00
b0 /
b0 .
b0 -
0,
b0 +
x*
1)
bx (
0'
x&
1%
0$
bx #
0"
0!
$end
#8000
1$
1'
#16000
0$
0'
#24000
1$
1'
#25000
0%
0)
#32000
0$
0'
#40000
b1 +
1$
1'
#41000
1&
1*
b0 #
b0 (
#42000
b101000 #
b101000 (
#43000
b1011010 #
b1011010 (
#48000
0$
0'
#56000
b10 +
1$
1'
#64000
0$
0'
#72000
b11 +
1$
1'
#80000
0$
0'
#88000
b100 +
1$
1'
#96000
0$
0'
#104000
b101 +
1$
1'
#112000
0$
0'
#120000
b110 +
1$
1'
#128000
0$
0'
#136000
b111 +
1$
1'
#144000
0$
0'
#152000
b1000 +
1$
1'
#160000
0$
0'
#168000
b1001 +
1$
1'
#176000
0$
0'
#184000
b1010 +
1$
1'
#192000
0$
0'
#200000
b1011 +
1$
1'
#208000
0$
0'
#216000
b1100 +
1$
1'
#224000
0$
0'
#232000
b1101 +
1$
1'
#240000
0$
0'
#248000
b1110 +
1$
1'
#256000
0$
0'
#264000
b1111 +
1$
1'
#272000
0$
0'
#280000
b1011010 .
b1 /
10
1"
1,
b0 +
1$
1'
#288000
0$
0'
#296000
b1 +
1$
1'
#304000
0$
0'
#312000
b10 +
1$
1'
#320000
0$
0'
#328000
b11 +
1$
1'
#336000
0$
0'
#344000
b100 +
1$
1'
#352000
0$
0'
#360000
b101 +
1$
1'
#368000
0$
0'
#376000
b110 +
1$
1'
#384000
0$
0'
#392000
b111 +
1$
1'
#400000
0$
0'
#408000
b1000 +
1$
1'
#416000
0$
0'
#424000
b1001 +
1$
1'
#432000
0$
0'
#440000
b1010 +
1$
1'
#448000
0$
0'
#456000
b1011 +
1$
1'
#464000
0$
0'
#472000
b1100 +
1$
1'
#480000
0$
0'
#488000
b1101 +
1$
1'
#496000
0$
0'
#504000
b1110 +
1$
1'
#512000
0$
0'
#520000
b1111 +
1$
1'
#528000
0$
0'
#536000
0,
b0 +
1$
1'
#544000
0$
0'
#552000
b1 +
1$
1'
#560000
0$
0'
#568000
b10 +
1$
1'
#576000
0$
0'
#584000
b11 +
1$
1'
#592000
0$
0'
#600000
b100 +
1$
1'
#608000
0$
0'
#616000
b101 +
1$
1'
#624000
0$
0'
#632000
b110 +
1$
1'
#640000
0$
0'
#648000
b111 +
1$
1'
#656000
0$
0'
#664000
b1000 +
1$
1'
#672000
0$
0'
#680000
b1001 +
1$
1'
#688000
0$
0'
#696000
b1010 +
1$
1'
#704000
0$
0'
#712000
b1011 +
1$
1'
#720000
0$
0'
#728000
b1100 +
1$
1'
#736000
0$
0'
#744000
b1101 +
1$
1'
#752000
0$
0'
#760000
b1110 +
1$
1'
#768000
0$
0'
#776000
b1111 +
1$
1'
#784000
0$
0'
#792000
11
1!
b10 /
00
0"
1,
b0 +
1$
1'
#800000
0$
0'
#808000
b1 +
1$
1'
#816000
0$
0'
#824000
b10 +
1$
1'
#832000
0$
0'
#840000
b11 +
1$
1'
#848000
0$
0'
#856000
b100 +
1$
1'
#864000
0$
0'
#872000
b101 +
1$
1'
#880000
0$
0'
#888000
b110 +
1$
1'
#896000
0$
0'
#904000
b111 +
1$
1'
#912000
0$
0'
#920000
b1000 +
1$
1'
#928000
0$
0'
#936000
b1001 +
1$
1'
#944000
0$
0'
#952000
b1010 +
1$
1'
#960000
0$
0'
#968000
b1011 +
1$
1'
#976000
0$
0'
#984000
b1100 +
1$
1'
#992000
0$
0'
#1000000
b1101 +
1$
1'
#1008000
0$
0'
#1016000
b1110 +
1$
1'
#1024000
0$
0'
#1032000
b1111 +
1$
1'
#1040000
0$
0'
#1048000
0,
b0 +
1$
1'
#1056000
0$
0'
#1064000
b1 +
1$
1'
#1072000
0$
0'
#1080000
b10 +
1$
1'
#1088000
0$
0'
#1096000
b11 +
1$
1'
#1104000
0$
0'
#1112000
b100 +
1$
1'
#1120000
0$
0'
#1128000
b101 +
1$
1'
#1136000
0$
0'
#1144000
b110 +
1$
1'
#1152000
0$
0'
#1160000
b111 +
1$
1'
#1168000
0$
0'
#1176000
b1000 +
1$
1'
#1184000
0$
0'
#1192000
b1001 +
1$
1'
#1200000
0$
0'
#1208000
b1010 +
1$
1'
#1216000
0$
0'
#1224000
b1011 +
1$
1'
#1232000
0$
0'
#1240000
b1100 +
1$
1'
#1248000
0$
0'
#1256000
b1101 +
1$
1'
#1264000
0$
0'
#1272000
b1110 +
1$
1'
#1280000
0$
0'
#1288000
b1111 +
1$
1'
#1296000
0$
0'
#1304000
b1 -
b101101 .
1,
b0 +
1$
1'
#1312000
0$
0'
#1320000
b1 +
1$
1'
#1328000
0$
0'
#1336000
b10 +
1$
1'
#1344000
0$
0'
#1352000
b11 +
1$
1'
#1360000
0$
0'
#1368000
b100 +
1$
1'
#1376000
0$
0'
#1384000
b101 +
1$
1'
#1392000
0$
0'
#1400000
b110 +
1$
1'
#1408000
0$
0'
#1416000
b111 +
1$
1'
#1424000
0$
0'
#1432000
b1000 +
1$
1'
#1440000
0$
0'
#1448000
b1001 +
1$
1'
#1456000
0$
0'
#1464000
b1010 +
1$
1'
#1472000
0$
0'
#1480000
b1011 +
1$
1'
#1488000
0$
0'
#1496000
b1100 +
1$
1'
#1504000
0$
0'
#1512000
b1101 +
1$
1'
#1520000
0$
0'
#1528000
b1110 +
1$
1'
#1536000
0$
0'
#1544000
b1111 +
1$
1'
#1552000
0$
0'
#1560000
0,
b0 +
1$
1'
#1568000
0$
0'
#1576000
b1 +
1$
1'
#1584000
0$
0'
#1592000
b10 +
1$
1'
#1600000
0$
0'
#1608000
b11 +
1$
1'
#1616000
0$
0'
#1624000
b100 +
1$
1'
#1632000
0$
0'
#1640000
b101 +
1$
1'
#1648000
0$
0'
#1656000
b110 +
1$
1'
#1664000
0$
0'
#1672000
b111 +
1$
1'
#1680000
0$
0'
#1688000
b1000 +
1$
1'
#1696000
0$
0'
#1704000
b1001 +
1$
1'
#1712000
0$
0'
#1720000
b1010 +
1$
1'
#1728000
0$
0'
#1736000
b1011 +
1$
1'
#1744000
0$
0'
#1752000
b1100 +
1$
1'
#1760000
0$
0'
#1768000
b1101 +
1$
1'
#1776000
0$
0'
#1784000
b1110 +
1$
1'
#1792000
0$
0'
#1800000
b1111 +
1$
1'
#1808000
0$
0'
#1816000
b10 -
b10110 .
10
1"
1,
b0 +
1$
1'
#1824000
0$
0'
#1832000
b1 +
1$
1'
#1840000
0$
0'
#1848000
b10 +
1$
1'
#1856000
0$
0'
#1864000
b11 +
1$
1'
#1872000
0$
0'
#1880000
b100 +
1$
1'
#1888000
0$
0'
#1896000
b101 +
1$
1'
#1904000
0$
0'
#1912000
b110 +
1$
1'
#1920000
0$
0'
#1928000
b111 +
1$
1'
#1936000
0$
0'
#1944000
b1000 +
1$
1'
#1952000
0$
0'
#1960000
b1001 +
1$
1'
#1968000
0$
0'
#1976000
b1010 +
1$
1'
#1984000
0$
0'
#1992000
b1011 +
1$
1'
#2000000
0$
0'
#2008000
b1100 +
1$
1'
#2016000
0$
0'
#2024000
b1101 +
1$
1'
#2032000
0$
0'
#2040000
b1110 +
1$
1'
#2048000
0$
0'
#2056000
b1111 +
1$
1'
#2064000
0$
0'
#2072000
0,
b0 +
1$
1'
#2080000
0$
0'
#2088000
b1 +
1$
1'
#2096000
0$
0'
#2104000
b10 +
1$
1'
#2112000
0$
0'
#2120000
b11 +
1$
1'
#2128000
0$
0'
#2136000
b100 +
1$
1'
#2144000
0$
0'
#2152000
b101 +
1$
1'
#2160000
0$
0'
#2168000
b110 +
1$
1'
#2176000
0$
0'
#2184000
b111 +
1$
1'
#2192000
0$
0'
#2200000
b1000 +
1$
1'
#2208000
0$
0'
#2216000
b1001 +
1$
1'
#2224000
0$
0'
#2232000
b1010 +
1$
1'
#2240000
0$
0'
#2248000
b1011 +
1$
1'
#2256000
0$
0'
#2264000
b1100 +
1$
1'
#2272000
0$
0'
#2280000
b1101 +
1$
1'
#2288000
0$
0'
#2296000
b1110 +
1$
1'
#2304000
0$
0'
#2312000
b1111 +
1$
1'
#2320000
0$
0'
#2328000
b11 -
b1011 .
00
0"
1,
b0 +
1$
1'
#2336000
0$
0'
#2344000
b1 +
1$
1'
#2352000
0$
0'
#2360000
b10 +
1$
1'
#2368000
0$
0'
#2376000
b11 +
1$
1'
#2384000
0$
0'
#2392000
b100 +
1$
1'
#2400000
0$
0'
#2408000
b101 +
1$
1'
#2416000
0$
0'
#2424000
b110 +
1$
1'
#2432000
0$
0'
#2440000
b111 +
1$
1'
#2448000
0$
0'
#2456000
b1000 +
1$
1'
#2464000
0$
0'
#2472000
b1001 +
1$
1'
#2480000
0$
0'
#2488000
b1010 +
1$
1'
#2496000
0$
0'
#2504000
b1011 +
1$
1'
#2512000
0$
0'
#2520000
b1100 +
1$
1'
#2528000
0$
0'
#2536000
b1101 +
1$
1'
#2544000
0$
0'
#2552000
b1110 +
1$
1'
#2560000
0$
0'
#2568000
b1111 +
1$
1'
#2576000
0$
0'
#2584000
0,
b0 +
1$
1'
#2592000
0$
0'
#2600000
b1 +
1$
1'
#2608000
0$
0'
#2616000
b10 +
1$
1'
#2624000
0$
0'
#2632000
b11 +
1$
1'
#2640000
0$
0'
#2648000
b100 +
1$
1'
#2656000
0$
0'
#2664000
b101 +
1$
1'
#2672000
0$
0'
#2680000
b110 +
1$
1'
#2688000
0$
0'
#2696000
b111 +
1$
1'
#2704000
0$
0'
#2712000
b1000 +
1$
1'
#2720000
0$
0'
#2728000
b1001 +
1$
1'
#2736000
0$
0'
#2744000
b1010 +
1$
1'
#2752000
0$
0'
#2760000
b1011 +
1$
1'
#2768000
0$
0'
#2776000
b1100 +
1$
1'
#2784000
0$
0'
#2792000
b1101 +
1$
1'
#2800000
0$
0'
#2808000
b1110 +
1$
1'
#2816000
0$
0'
#2824000
b1111 +
1$
1'
#2832000
0$
0'
#2840000
b100 -
b101 .
10
1"
1,
b0 +
1$
1'
#2848000
0$
0'
#2856000
b1 +
1$
1'
#2864000
0$
0'
#2872000
b10 +
1$
1'
#2880000
0$
0'
#2888000
b11 +
1$
1'
#2896000
0$
0'
#2904000
b100 +
1$
1'
#2912000
0$
0'
#2920000
b101 +
1$
1'
#2928000
0$
0'
#2936000
b110 +
1$
1'
#2944000
0$
0'
#2952000
b111 +
1$
1'
#2960000
0$
0'
#2968000
b1000 +
1$
1'
#2976000
0$
0'
#2984000
b1001 +
1$
1'
#2992000
0$
0'
#3000000
b1010 +
1$
1'
#3008000
0$
0'
#3016000
b1011 +
1$
1'
#3024000
0$
0'
#3032000
b1100 +
1$
1'
#3040000
0$
0'
#3048000
b1101 +
1$
1'
#3056000
0$
0'
#3064000
b1110 +
1$
1'
#3072000
0$
0'
#3080000
b1111 +
1$
1'
#3088000
0$
0'
#3096000
0,
b0 +
1$
1'
#3104000
0$
0'
#3112000
b1 +
1$
1'
#3120000
0$
0'
#3128000
b10 +
1$
1'
#3136000
0$
0'
#3144000
b11 +
1$
1'
#3152000
0$
0'
#3160000
b100 +
1$
1'
#3168000
0$
0'
#3176000
b101 +
1$
1'
#3184000
0$
0'
#3192000
b110 +
1$
1'
#3200000
0$
0'
#3208000
b111 +
1$
1'
#3216000
0$
0'
#3224000
b1000 +
1$
1'
#3232000
0$
0'
#3240000
b1001 +
1$
1'
#3248000
0$
0'
#3256000
b1010 +
1$
1'
#3264000
0$
0'
#3272000
b1011 +
1$
1'
#3280000
0$
0'
#3288000
b1100 +
1$
1'
#3296000
0$
0'
#3304000
b1101 +
1$
1'
#3312000
0$
0'
#3320000
b1110 +
1$
1'
#3328000
0$
0'
#3336000
b1111 +
1$
1'
#3344000
0$
0'
#3352000
b101 -
b10 .
1,
b0 +
1$
1'
#3360000
0$
0'
#3368000
b1 +
1$
1'
#3376000
0$
0'
#3384000
b10 +
1$
1'
#3392000
0$
0'
#3400000
b11 +
1$
1'
#3408000
0$
0'
#3416000
b100 +
1$
1'
#3424000
0$
0'
#3432000
b101 +
1$
1'
#3440000
0$
0'
#3448000
b110 +
1$
1'
#3456000
0$
0'
#3464000
b111 +
1$
1'
#3472000
0$
0'
#3480000
b1000 +
1$
1'
#3488000
0$
0'
#3496000
b1001 +
1$
1'
#3504000
0$
0'
#3512000
b1010 +
1$
1'
#3520000
0$
0'
#3528000
b1011 +
1$
1'
#3536000
0$
0'
#3544000
b1100 +
1$
1'
#3552000
0$
0'
#3560000
b1101 +
1$
1'
#3568000
0$
0'
#3576000
b1110 +
1$
1'
#3584000
0$
0'
#3592000
b1111 +
1$
1'
#3600000
0$
0'
#3608000
0,
b0 +
1$
1'
#3616000
0$
0'
#3624000
b1 +
1$
1'
#3632000
0$
0'
#3640000
b10 +
1$
1'
#3648000
0$
0'
#3656000
b11 +
1$
1'
#3664000
0$
0'
#3672000
b100 +
1$
1'
#3680000
0$
0'
#3688000
b101 +
1$
1'
#3696000
0$
0'
#3704000
b110 +
1$
1'
#3712000
0$
0'
#3720000
b111 +
1$
1'
#3728000
0$
0'
#3736000
b1000 +
1$
1'
#3744000
0$
0'
#3752000
b1001 +
1$
1'
#3760000
0$
0'
#3768000
b1010 +
1$
1'
#3776000
0$
0'
#3784000
b1011 +
1$
1'
#3792000
0$
0'
#3800000
b1100 +
1$
1'
#3808000
0$
0'
#3816000
b1101 +
1$
1'
#3824000
0$
0'
#3832000
b1110 +
1$
1'
#3840000
0$
0'
#3848000
b1111 +
1$
1'
#3856000
0$
0'
#3864000
b110 -
b1 .
00
0"
1,
b0 +
1$
1'
#3872000
0$
0'
#3880000
b1 +
1$
1'
#3888000
0$
0'
#3896000
b10 +
1$
1'
#3904000
0$
0'
#3912000
b11 +
1$
1'
#3920000
0$
0'
#3928000
b100 +
1$
1'
#3936000
0$
0'
#3944000
b101 +
1$
1'
#3952000
0$
0'
#3960000
b110 +
1$
1'
#3968000
0$
0'
#3976000
b111 +
1$
1'
#3984000
0$
0'
#3992000
b1000 +
1$
1'
#4000000
0$
0'
#4008000
b1001 +
1$
1'
#4016000
0$
0'
#4024000
b1010 +
1$
1'
#4032000
0$
0'
#4040000
b1011 +
1$
1'
#4048000
0$
0'
#4056000
b1100 +
1$
1'
#4064000
0$
0'
#4072000
b1101 +
1$
1'
#4080000
0$
0'
#4088000
b1110 +
1$
1'
#4096000
0$
0'
#4104000
b1111 +
1$
1'
#4112000
0$
0'
#4120000
0,
b0 +
1$
1'
#4128000
0$
0'
#4136000
b1 +
1$
1'
#4144000
0$
0'
#4152000
b10 +
1$
1'
#4160000
0$
0'
#4168000
b11 +
1$
1'
#4176000
0$
0'
#4184000
b100 +
1$
1'
#4192000
0$
0'
#4200000
b101 +
1$
1'
#4208000
0$
0'
#4216000
b110 +
1$
1'
#4224000
0$
0'
#4232000
b111 +
1$
1'
#4240000
0$
0'
#4248000
b1000 +
1$
1'
#4256000
0$
0'
#4264000
b1001 +
1$
1'
#4272000
0$
0'
#4280000
b1010 +
1$
1'
#4288000
0$
0'
#4296000
b1011 +
1$
1'
#4304000
0$
0'
#4312000
b1100 +
1$
1'
#4320000
0$
0'
#4328000
b1101 +
1$
1'
#4336000
0$
0'
#4344000
b1110 +
1$
1'
#4352000
0$
0'
#4360000
b1111 +
1$
1'
#4368000
0$
0'
#4376000
b111 -
b0 .
10
1"
1,
b0 +
1$
1'
#4384000
0$
0'
#4392000
b1 +
1$
1'
#4400000
0$
0'
#4408000
b10 +
1$
1'
#4416000
0$
0'
#4424000
b11 +
1$
1'
#4432000
0$
0'
#4440000
b100 +
1$
1'
#4448000
0$
0'
#4456000
b101 +
1$
1'
#4464000
0$
0'
#4472000
b110 +
1$
1'
#4480000
0$
0'
#4488000
b111 +
1$
1'
#4496000
0$
0'
#4504000
b1000 +
1$
1'
#4512000
0$
0'
#4520000
b1001 +
1$
1'
#4528000
0$
0'
#4536000
b1010 +
1$
1'
#4544000
0$
0'
#4552000
b1011 +
1$
1'
#4560000
0$
0'
#4568000
b1100 +
1$
1'
#4576000
0$
0'
#4584000
b1101 +
1$
1'
#4592000
0$
0'
#4600000
b1110 +
1$
1'
#4608000
0$
0'
#4616000
b1111 +
1$
1'
#4624000
0$
0'
#4632000
0,
b0 +
1$
1'
#4640000
0$
0'
#4648000
b1 +
1$
1'
#4656000
0$
0'
#4664000
b10 +
1$
1'
#4672000
0$
0'
#4680000
b11 +
1$
1'
#4688000
0$
0'
#4696000
b100 +
1$
1'
#4704000
0$
0'
#4712000
b101 +
1$
1'
#4720000
0$
0'
#4728000
b110 +
1$
1'
#4736000
0$
0'
#4744000
b111 +
1$
1'
#4752000
0$
0'
#4760000
b1000 +
1$
1'
#4768000
0$
0'
#4776000
b1001 +
1$
1'
#4784000
0$
0'
#4792000
b1010 +
1$
1'
#4800000
0$
0'
#4808000
b1011 +
1$
1'
#4816000
0$
0'
#4824000
b1100 +
1$
1'
#4832000
0$
0'
#4840000
b1101 +
1$
1'
#4848000
0$
0'
#4856000
b1110 +
1$
1'
#4864000
0$
0'
#4872000
b1111 +
1$
1'
#4880000
0$
0'
#4888000
b11 /
00
0"
1,
b0 +
1$
1'
#4896000
0$
0'
#4904000
b1 +
1$
1'
#4912000
0$
0'
#4920000
b10 +
1$
1'
#4928000
0$
0'
#4936000
b11 +
1$
1'
#4944000
0$
0'
#4952000
b100 +
1$
1'
#4960000
0$
0'
#4968000
b101 +
1$
1'
#4976000
0$
0'
#4984000
b110 +
1$
1'
#4992000
0$
0'
#5000000
b111 +
1$
1'
#5008000
0$
0'
#5016000
b1000 +
1$
1'
#5024000
0$
0'
#5032000
b1001 +
1$
1'
#5040000
0$
0'
#5048000
b1010 +
1$
1'
#5056000
0$
0'
#5064000
b1011 +
1$
1'
#5072000
0$
0'
#5080000
b1100 +
1$
1'
#5088000
0$
0'
#5096000
b1101 +
1$
1'
#5104000
0$
0'
#5112000
b1110 +
1$
1'
#5120000
0$
0'
#5128000
b1111 +
1$
1'
#5136000
0$
0'
#5144000
0,
b0 +
1$
1'
#5152000
0$
0'
#5160000
b1 +
1$
1'
#5168000
0$
0'
#5176000
b10 +
1$
1'
#5184000
0$
0'
#5192000
b11 +
1$
1'
#5200000
0$
0'
#5208000
b100 +
1$
1'
#5216000
0$
0'
#5224000
b101 +
1$
1'
#5232000
0$
0'
#5240000
b110 +
1$
1'
#5248000
0$
0'
#5256000
b111 +
1$
1'
#5264000
0$
0'
#5272000
b1000 +
1$
1'
#5280000
0$
0'
#5288000
b1001 +
1$
1'
#5296000
0$
0'
#5304000
b1010 +
1$
1'
#5312000
0$
0'
#5320000
b1011 +
1$
1'
#5328000
0$
0'
#5336000
b1100 +
1$
1'
#5344000
0$
0'
#5352000
b1101 +
1$
1'
#5360000
0$
0'
#5368000
b1110 +
1$
1'
#5376000
0$
0'
#5384000
b1111 +
1$
1'
#5392000
0$
0'
#5400000
01
0!
b0 /
10
1"
1,
b0 +
1$
1'
#5408000
0$
0'
#5416000
b1 +
1$
1'
#5424000
0$
0'
#5432000
b10 +
1$
1'
#5440000
0$
0'
#5448000
b11 +
1$
1'
#5456000
0$
0'
#5464000
b100 +
1$
1'
#5472000
0$
0'
#5480000
b101 +
1$
1'
#5488000
0$
0'
#5496000
b110 +
1$
1'
#5504000
0$
0'
#5512000
b111 +
1$
1'
#5520000
0$
0'
#5528000
b1000 +
1$
1'
#5536000
0$
0'
#5544000
b1001 +
1$
1'
#5552000
0$
0'
#5560000
b1010 +
1$
1'
#5568000
0$
0'
#5576000
b1011 +
1$
1'
#5584000
0$
0'
#5592000
b1100 +
1$
1'
#5600000
0$
0'
#5608000
b1101 +
1$
1'
#5616000
0$
0'
#5624000
b1110 +
1$
1'
#5632000
0$
0'
#5640000
b1111 +
1$
1'
#5648000
0$
0'
#5656000
0,
b0 +
1$
1'
#5664000
0$
0'
#5672000
b1 +
1$
1'
#5680000
0$
0'
#5688000
b10 +
1$
1'
#5696000
0$
0'
#5704000
b11 +
1$
1'
#5712000
0$
0'
#5720000
b100 +
1$
1'
#5728000
0$
0'
#5736000
b101 +
1$
1'
#5744000
0$
0'
#5752000
b110 +
1$
1'
#5760000
0$
0'
#5768000
b111 +
1$
1'
#5776000
0$
0'
#5784000
b1000 +
1$
1'
#5792000
0$
0'
#5800000
b1001 +
1$
1'
#5808000
0$
0'
#5816000
b1010 +
1$
1'
#5824000
0$
0'
#5832000
b1011 +
1$
1'
#5840000
0$
0'
#5848000
b1100 +
1$
1'
#5856000
0$
0'
#5864000
b1101 +
1$
1'
#5872000
0$
0'
#5880000
b1110 +
1$
1'
#5888000
0$
0'
#5896000
b1111 +
1$
1'
#5904000
0$
0'
#5912000
b1011010 .
b1 /
b0 -
1,
b0 +
1$
1'
#5920000
0$
0'
#5928000
b1 +
1$
1'
#5936000
0$
0'
#5944000
b10 +
1$
1'
#5952000
0$
0'
#5960000
b11 +
1$
1'
#5968000
0$
0'
#5976000
b100 +
1$
1'
#5984000
0$
0'
#5992000
b101 +
1$
1'
#6000000
0$
0'
#6008000
b110 +
1$
1'
#6016000
0$
0'
#6024000
b111 +
1$
1'
#6032000
0$
0'
#6040000
b1000 +
1$
1'
#6048000
0$
0'
#6056000
b1001 +
1$
1'
#6064000
0$
0'
#6072000
b1010 +
1$
1'
#6080000
0$
0'
#6088000
b1011 +
1$
1'
#6096000
0$
0'
#6104000
b1100 +
1$
1'
#6112000
0$
0'
#6120000
b1101 +
1$
1'
#6128000
0$
0'
#6136000
b1110 +
1$
1'
#6144000
0$
0'
#6152000
b1111 +
1$
1'
#6160000
0$
0'
#6168000
0,
b0 +
1$
1'
#6176000
0$
0'
#6184000
b1 +
1$
1'
#6192000
0$
0'
#6200000
b10 +
1$
1'
#6208000
0$
0'
#6216000
b11 +
1$
1'
#6224000
0$
0'
#6232000
b100 +
1$
1'
#6240000
0$
0'
#6248000
b101 +
1$
1'
#6256000
0$
0'
#6264000
b110 +
1$
1'
#6272000
0$
0'
#6280000
b111 +
1$
1'
#6288000
0$
0'
#6296000
b1000 +
1$
1'
#6304000
0$
0'
#6312000
b1001 +
1$
1'
#6320000
0$
0'
#6328000
b1010 +
1$
1'
#6336000
0$
0'
#6344000
b1011 +
1$
1'
#6352000
0$
0'
#6360000
b1100 +
1$
1'
#6368000
0$
0'
#6376000
b1101 +
1$
1'
#6384000
0$
0'
#6392000
b1110 +
1$
1'
#6400000
0$
0'
#6408000
b1111 +
1$
1'
#6416000
0$
0'
#6424000
11
1!
b10 /
00
0"
1,
b0 +
1$
1'
#6432000
0$
0'
#6440000
b1 +
1$
1'
#6448000
0$
0'
#6456000
b10 +
1$
1'
#6464000
0$
0'
#6472000
b11 +
1$
1'
#6480000
0$
0'
#6488000
b100 +
1$
1'
#6496000
0$
0'
#6504000
b101 +
1$
1'
#6512000
0$
0'
#6520000
b110 +
1$
1'
#6528000
0$
0'
#6536000
b111 +
1$
1'
#6544000
0$
0'
#6552000
b1000 +
1$
1'
#6560000
0$
0'
#6568000
b1001 +
1$
1'
#6576000
0$
0'
#6584000
b1010 +
1$
1'
#6592000
0$
0'
#6600000
b1011 +
1$
1'
#6608000
0$
0'
#6616000
b1100 +
1$
1'
#6624000
0$
0'
#6632000
b1101 +
1$
1'
#6640000
0$
0'
#6648000
b1110 +
1$
1'
#6656000
0$
0'
#6664000
b1111 +
1$
1'
#6672000
0$
0'
#6680000
0,
b0 +
1$
1'
#6688000
0$
0'
#6696000
b1 +
1$
1'
#6704000
0$
0'
#6712000
b10 +
1$
1'
#6720000
0$
0'
#6728000
b11 +
1$
1'
#6736000
0$
0'
#6744000
b100 +
1$
1'
#6752000
0$
0'
#6760000
b101 +
1$
1'
#6768000
0$
0'
#6776000
b110 +
1$
1'
#6784000
0$
0'
#6792000
b111 +
1$
1'
#6800000
0$
0'
#6808000
b1000 +
1$
1'
#6816000
0$
0'
#6824000
b1001 +
1$
1'
#6832000
0$
0'
#6840000
b1010 +
1$
1'
#6848000
0$
0'
#6856000
b1011 +
1$
1'
#6864000
0$
0'
#6872000
b1100 +
1$
1'
#6880000
0$
0'
#6888000
b1101 +
1$
1'
#6896000
0$
0'
#6904000
b1110 +
1$
1'
#6912000
0$
0'
#6920000
b1111 +
1$
1'
#6928000
0$
0'
#6936000
b1 -
b101101 .
1,
b0 +
1$
1'
#6944000
0$
0'
#6952000
b1 +
1$
1'
#6960000
0$
0'
#6968000
b10 +
1$
1'
#6976000
0$
0'
#6984000
b11 +
1$
1'
#6992000
0$
0'
#7000000
b100 +
1$
1'
#7008000
0$
0'
#7016000
b101 +
1$
1'
#7024000
0$
0'
#7032000
b110 +
1$
1'
#7040000
0$
0'
#7048000
b111 +
1$
1'
#7056000
0$
0'
#7064000
b1000 +
1$
1'
#7072000
0$
0'
#7080000
b1001 +
1$
1'
#7088000
0$
0'
#7096000
b1010 +
1$
1'
#7104000
0$
0'
#7112000
b1011 +
1$
1'
#7120000
0$
0'
#7128000
b1100 +
1$
1'
#7136000
0$
0'
#7144000
b1101 +
1$
1'
#7152000
0$
0'
#7160000
b1110 +
1$
1'
#7168000
0$
0'
#7176000
b1111 +
1$
1'
#7184000
0$
0'
#7192000
0,
b0 +
1$
1'
#7200000
0$
0'
#7208000
b1 +
1$
1'
#7216000
0$
0'
#7224000
b10 +
1$
1'
#7232000
0$
0'
#7240000
b11 +
1$
1'
#7248000
0$
0'
#7256000
b100 +
1$
1'
#7264000
0$
0'
#7272000
b101 +
1$
1'
#7280000
0$
0'
#7288000
b110 +
1$
1'
#7296000
0$
0'
#7304000
b111 +
1$
1'
#7312000
0$
0'
#7320000
b1000 +
1$
1'
#7328000
0$
0'
#7336000
b1001 +
1$
1'
#7344000
0$
0'
#7352000
b1010 +
1$
1'
#7360000
0$
0'
#7368000
b1011 +
1$
1'
#7376000
0$
0'
#7384000
b1100 +
1$
1'
#7392000
0$
0'
#7400000
b1101 +
1$
1'
#7408000
0$
0'
#7416000
b1110 +
1$
1'
#7424000
0$
0'
#7432000
b1111 +
1$
1'
#7440000
0$
0'
#7448000
b10 -
b10110 .
10
1"
1,
b0 +
1$
1'
#7456000
0$
0'
#7464000
b1 +
1$
1'
#7472000
0$
0'
#7480000
b10 +
1$
1'
#7488000
0$
0'
#7496000
b11 +
1$
1'
#7504000
0$
0'
#7512000
b100 +
1$
1'
#7520000
0$
0'
#7528000
b101 +
1$
1'
#7536000
0$
0'
#7544000
b110 +
1$
1'
#7552000
0$
0'
#7560000
b111 +
1$
1'
#7568000
0$
0'
