hdmits-cmp/cores/adpcm/rtl/adpcm.v
module adpcm(
  input  wire        clk,
  input  wire        rst,
  input  wire        eo,
  input  wire        in_en,
  input  wire [15:0] din,
  output wire        out_en,
  output wire [15:0] dout
);

reg [15:0] bp;
reg [15:0] y,cbcr;
reg [15:0] out;
reg        oen;
wire [7:0] yin  = din[7:0 ]; 
wire [7:0] rbin = din[15:8];
wire [7:0] ybp  = bp [7:0 ];
wire [7:0] rbbp = bp [15:8];

wire [15:0]yout = (~eo) ? {cbcr[7:0], y[7:0]} : out;

assign dout = (oen) ? yout : 16'd0;
assign out_en = oen;
always@(posedge clk)begin
  if(rst)begin
	  bp   <= 16'd0;
	  y    <= 16'd0;
	  cbcr <= 16'd0;
	  out  <= 16'd0;
  end else begin
    oen <= in_en;
	bp <= din;
	if(eo)begin
      if(yin > ybp)
        y    <= (({8'd0,yin} - {8'd0,ybp}) * 8 + 127)/*/254*/;
      else
        y    <= (({8'd0,ybp} - {8'd0,yin}) * 8 + 127)/*/254*/;
      if(rbin > rbbp)
        cbcr <= (({8'd0,rbin} - {8'd0,rbbp}) * 8 + 127)/*/254*/;
      else
		cbcr <= (({8'd0,rbbp} - {8'd0,rbin}) * 8 + 127)/*/254*/;
	end else begin
      out <= din;
    end
  end
end

endmodule

hdmits-cmp/cores/adpcm/test/tb_adpcm.v
`timescale 1ns / 1ps

module tb_adpcm();


//
// System Clock 125MHz
//
reg sys_clk;
initial sys_clk = 1'b0;
always #6.74 sys_clk = ~sys_clk;

//
// Test Bench
//
reg sys_rst;
reg eo,en; // ever or odd bit
wire [15:0]in;
wire [15:0]out;
wire oen;

adpcm test(
  .clk(sys_clk),
  .rst(sys_rst),
  .eo(eo),
  .in_en(en),
  .din(in),
  .out_en(oen),
  .dout(out)
);


//
// a clock
//
task waitclock;
begin
	@(posedge sys_clk);
	#1;
end
endtask

always @ (posedge sys_clk)
  if(sys_rst)
    eo <= 1'b0;
  else
    eo <= ~eo;

reg [7:0]cnt;
always @ (posedge sys_clk)begin
  if(sys_rst)begin
    en <= 1'd0;
	cnt <= 8'd0;
  end else begin
    if(cnt == 8'd15)
	  cnt <= 8'd0;	
	else
	  cnt <= cnt + 8'd1;

	if(cnt == 8'd1)
	  en <= ~en;
  end
end

reg [7:0]a,b;
assign in = {a,b};
always @ (posedge sys_clk) begin
  if(sys_rst)begin
    a <= 8'd0;
    b <= 8'd0;
  end else begin
    a <= a + 8'd18;
    b <= b + 8'd34;
  end
end

//
// Scinario
//

initial begin
	$dumpfile("./test.vcd");
	$dumpvars(0, tb_adpcm);
	sys_rst = 1'b1;

	waitclock;
	waitclock;

	sys_rst = 1'b0;

	waitclock;


	#100000;
	$finish;
end

endmodule

hdmits-cmp/cores/adpcm/test/test.vcd
$date
	Sat Mar 15 21:00:27 2014
$end
$version
	Icarus Verilog
$end
$timescale
	1ps
$end
$scope module tb_adpcm $end
$var wire 16 ! in [15:0] $end
$var wire 1 " oen $end
$var wire 16 # out [15:0] $end
$var reg 8 $ a [7:0] $end
$var reg 8 % b [7:0] $end
$var reg 8 & cnt [7:0] $end
$var reg 1 ' en $end
$var reg 1 ( eo $end
$var reg 1 ) sys_clk $end
$var reg 1 * sys_rst $end
$scope module test $end
$var wire 1 + clk $end
$var wire 16 , din [15:0] $end
$var wire 16 - dout [15:0] $end
$var wire 1 . eo $end
$var wire 1 / in_en $end
$var wire 1 " out_en $end
$var wire 8 0 rbbp [7:0] $end
$var wire 8 1 rbin [7:0] $end
$var wire 1 2 rst $end
$var wire 8 3 ybp [7:0] $end
$var wire 8 4 yin [7:0] $end
$var wire 16 5 yout [15:0] $end
$var reg 16 6 bp [15:0] $end
$var reg 16 7 cbcr [15:0] $end
$var reg 1 8 oen $end
$var reg 16 9 out [15:0] $end
$var reg 16 : y [15:0] $end
$upscope $end
$scope task waitclock $end
$upscope $end
$upscope $end
$enddefinitions $end
#0
$dumpvars
bx :
bx 9
x8
bx 7
bx 6
bx 5
bx 4
bx 3
12
bx 1
bx 0
x/
x.
bx -
bx ,
0+
1*
0)
x(
x'
bx &
bx %
bx $
bx #
x"
bx !
$end
#6740
b0 #
b0 -
b0 5
b0 3
b0 0
b0 4
b0 1
b0 9
b0 7
b0 :
b0 6
0(
0.
b0 &
0'
0/
b0 %
b0 $
b0 !
b0 ,
1)
1+
#13480
0)
0+
#20220
1)
1+
#21220
0*
02
#26960
0)
0+
#33700
b100010 4
b10010 1
08
0"
1(
1.
b1 &
b100010 %
b10010 $
b1001000100010 !
b1001000100010 ,
1)
1+
#40440
0)
0+
#47180
b111110001111 5
b1000100 4
b100100 1
b100010 3
b10010 0
b1000100 %
b100100 $
b10010001000100 !
b10010001000100 ,
1'
1/
b10 &
0(
0.
b100001111 7
b110001111 :
b1001000100010 6
1)
1+
#53920
0)
0+
#60660
b10010001000100 5
b1000100 3
b100100 0
b10010001000100 #
b10010001000100 -
b1100110 4
b110110 1
b10010001000100 9
b10010001000100 6
18
1"
1(
1.
b11 &
b1100110 %
b110110 $
b11011001100110 !
b11011001100110 ,
1)
1+
#67400
0)
0+
#74140
b111110001111 #
b111110001111 -
b111110001111 5
b10001000 4
b1001000 1
b1100110 3
b110110 0
b10001000 %
b1001000 $
b100100010001000 !
b100100010001000 ,
b100 &
0(
0.
b11011001100110 6
1)
1+
#80880
0)
0+
#87620
b100100010001000 #
b100100010001000 -
b100100010001000 5
b10001000 3
b1001000 0
b10101010 4
b1011010 1
b100100010001000 9
b100100010001000 6
1(
1.
b101 &
b10101010 %
b1011010 $
b101101010101010 !
b101101010101010 ,
1)
1+
#94360
0)
0+
#101100
b111110001111 #
b111110001111 -
b111110001111 5
b11001100 4
b1101100 1
b10101010 3
b1011010 0
b11001100 %
b1101100 $
b110110011001100 !
b110110011001100 ,
b110 &
0(
0.
b101101010101010 6
1)
1+
#107840
0)
0+
#114580
b110110011001100 #
b110110011001100 -
b110110011001100 5
b11001100 3
b1101100 0
b11101110 4
b1111110 1
b110110011001100 9
b110110011001100 6
1(
1.
b111 &
b11101110 %
b1111110 $
b111111011101110 !
b111111011101110 ,
1)
1+
#121320
0)
0+
#128060
b111110001111 #
b111110001111 -
b111110001111 5
b10000 4
b10010000 1
b11101110 3
b1111110 0
b10000 %
b10010000 $
b1001000000010000 !
b1001000000010000 ,
b1000 &
0(
0.
b111111011101110 6
1)
1+
#134800
0)
0+
#141540
b1001000000010000 #
b1001000000010000 -
b1001000000010000 5
b10000 3
b10010000 0
b110010 4
b10100010 1
b1001000000010000 9
b1001000000010000 6
1(
1.
b1001 &
b110010 %
b10100010 $
b1010001000110010 !
b1010001000110010 ,
1)
1+
#148280
0)
0+
#155020
b111110001111 #
b111110001111 -
b111110001111 5
b1010100 4
b10110100 1
b110010 3
b10100010 0
b1010100 %
b10110100 $
b1011010001010100 !
b1011010001010100 ,
b1010 &
0(
0.
b1010001000110010 6
1)
1+
#161760
0)
0+
#168500
b1011010001010100 #
b1011010001010100 -
b1011010001010100 5
b1010100 3
b10110100 0
b1110110 4
b11000110 1
b1011010001010100 9
b1011010001010100 6
1(
1.
b1011 &
b1110110 %
b11000110 $
b1100011001110110 !
b1100011001110110 ,
1)
1+
#175240
0)
0+
#181980
b111110001111 #
b111110001111 -
b111110001111 5
b10011000 4
b11011000 1
b1110110 3
b11000110 0
b10011000 %
b11011000 $
b1101100010011000 !
b1101100010011000 ,
b1100 &
0(
0.
b1100011001110110 6
1)
1+
#188720
0)
0+
#195460
b1101100010011000 #
b1101100010011000 -
b1101100010011000 5
b10011000 3
b11011000 0
b10111010 4
b11101010 1
b1101100010011000 9
b1101100010011000 6
1(
1.
b1101 &
b10111010 %
b11101010 $
b1110101010111010 !
b1110101010111010 ,
1)
1+
#202200
0)
0+
#208940
b111110001111 #
b111110001111 -
b111110001111 5
b11011100 4
b11111100 1
b10111010 3
b11101010 0
b11011100 %
b11111100 $
b1111110011011100 !
b1111110011011100 ,
b1110 &
0(
0.
b1110101010111010 6
1)
1+
#215680
0)
0+
#222420
b1111110011011100 #
b1111110011011100 -
b1111110011011100 5
b11011100 3
b11111100 0
b11111110 4
b1110 1
b1111110011011100 9
b1111110011011100 6
1(
1.
b1111 &
b11111110 %
b1110 $
b111011111110 !
b111011111110 ,
1)
1+
#229160
0)
0+
#235900
b1110111110001111 #
b1110111110001111 -
b1110111110001111 5
b100000 4
b100000 1
b11111110 3
b1110 0
b100000 %
b100000 $
b10000000100000 !
b10000000100000 ,
b0 &
0(
0.
b11111101111 7
b111011111110 6
1)
1+
#242640
0)
0+
#249380
b10000000100000 #
b10000000100000 -
b10000000100000 5
b100000 3
b100000 0
b1000010 4
b110010 1
b10000000100000 9
b10000000100000 6
1(
1.
b1 &
b1000010 %
b110010 $
b11001001000010 !
b11001001000010 ,
1)
1+
#256120
0)
0+
#262860
b111110001111 #
b111110001111 -
b111110001111 5
b1100100 4
b1000100 1
b1000010 3
b110010 0
b1100100 %
b1000100 $
b100010001100100 !
b100010001100100 ,
0'
0/
b10 &
0(
0.
b100001111 7
b11001001000010 6
1)
1+
#269600
0)
0+
#276340
b100010001100100 5
b1100100 3
b1000100 0
b0 #
b0 -
b10000110 4
b1010110 1
b100010001100100 9
b100010001100100 6
08
0"
1(
1.
b11 &
b10000110 %
b1010110 $
b101011010000110 !
b101011010000110 ,
1)
1+
#283080
0)
0+
#289820
b111110001111 5
b10101000 4
b1101000 1
b10000110 3
b1010110 0
b10101000 %
b1101000 $
b110100010101000 !
b110100010101000 ,
b100 &
0(
0.
b101011010000110 6
1)
1+
#296560
0)
0+
#303300
b110100010101000 5
b10101000 3
b1101000 0
b11001010 4
b1111010 1
b110100010101000 9
b110100010101000 6
1(
1.
b101 &
b11001010 %
b1111010 $
b111101011001010 !
b111101011001010 ,
1)
1+
#310040
0)
0+
#316780
b111110001111 5
b11101100 4
b10001100 1
b11001010 3
b1111010 0
b11101100 %
b10001100 $
b1000110011101100 !
b1000110011101100 ,
b110 &
0(
0.
b111101011001010 6
1)
1+
#323520
0)
0+
#330260
b1000110011101100 5
b11101100 3
b10001100 0
b1110 4
b10011110 1
b1000110011101100 9
b1000110011101100 6
1(
1.
b111 &
b1110 %
b10011110 $
b1001111000001110 !
b1001111000001110 ,
1)
1+
#337000
0)
0+
#343740
b111101101111 5
b110000 4
b10110000 1
b1110 3
b10011110 0
b110000 %
b10110000 $
b1011000000110000 !
b1011000000110000 ,
b1000 &
0(
0.
b11101101111 :
b1001111000001110 6
1)
1+
#350480
0)
0+
#357220
b1011000000110000 5
b110000 3
b10110000 0
b1010010 4
b11000010 1
b1011000000110000 9
b1011000000110000 6
1(
1.
b1001 &
b1010010 %
b11000010 $
b1100001001010010 !
b1100001001010010 ,
1)
1+
#363960
0)
0+
#370700
b111110001111 5
b1110100 4
b11010100 1
b1010010 3
b11000010 0
b1110100 %
b11010100 $
b1101010001110100 !
b1101010001110100 ,
b1010 &
0(
0.
b110001111 :
b1100001001010010 6
1)
1+
#377440
0)
0+
#384180
b1101010001110100 5
b1110100 3
b11010100 0
b10010110 4
b11100110 1
b1101010001110100 9
b1101010001110100 6
1(
1.
b1011 &
b10010110 %
b11100110 $
b1110011010010110 !
b1110011010010110 ,
1)
1+
#390920
0)
0+
#397660
b111110001111 5
b10111000 4
b11111000 1
b10010110 3
b11100110 0
b10111000 %
b11111000 $
b1111100010111000 !
b1111100010111000 ,
b1100 &
0(
0.
b1110011010010110 6
1)
1+
#404400
0)
0+
#411140
b1111100010111000 5
b10111000 3
b11111000 0
b11011010 4
b1010 1
b1111100010111000 9
b1111100010111000 6
1(
1.
b1101 &
b11011010 %
b1010 $
b101011011010 !
b101011011010 ,
1)
1+
#417880
0)
0+
#424620
b1110111110001111 5
b11111100 4
b11100 1
b11011010 3
b1010 0
b11111100 %
b11100 $
b1110011111100 !
b1110011111100 ,
b1110 &
0(
0.
b11111101111 7
b101011011010 6
1)
1+
#431360
0)
0+
#438100
b1110011111100 5
b11111100 3
b11100 0
b11110 4
b101110 1
b1110011111100 9
b1110011111100 6
1(
1.
b1111 &
b11110 %
b101110 $
b10111000011110 !
b10111000011110 ,
1)
1+
#444840
0)
0+
#451580
b111101101111 5
b1000000 4
b1000000 1
b11110 3
b101110 0
b1000000 %
b1000000 $
b100000001000000 !
b100000001000000 ,
b0 &
0(
0.
b100001111 7
b11101101111 :
b10111000011110 6
1)
1+
#458320
0)
0+
#465060
b100000001000000 5
b1000000 3
b1000000 0
b1100010 4
b1010010 1
b100000001000000 9
b100000001000000 6
1(
1.
b1 &
b1100010 %
b1010010 $
b101001001100010 !
b101001001100010 ,
1)
1+
#471800
0)
0+
#478540
b111110001111 5
b10000100 4
b1100100 1
b1100010 3
b1010010 0
b10000100 %
b1100100 $
b110010010000100 !
b110010010000100 ,
1'
1/
b10 &
0(
0.
b110001111 :
b101001001100010 6
1)
1+
#485280
0)
0+
#492020
b110010010000100 5
b10000100 3
b1100100 0
b110010010000100 #
b110010010000100 -
b10100110 4
b1110110 1
b110010010000100 9
b110010010000100 6
18
1"
1(
1.
b11 &
b10100110 %
b1110110 $
b111011010100110 !
b111011010100110 ,
1)
1+
#498760
0)
0+
#505500
b111110001111 #
b111110001111 -
b111110001111 5
b11001000 4
b10001000 1
b10100110 3
b1110110 0
b11001000 %
b10001000 $
b1000100011001000 !
b1000100011001000 ,
b100 &
0(
0.
b111011010100110 6
1)
1+
#512240
0)
0+
#518980
b1000100011001000 #
b1000100011001000 -
b1000100011001000 5
b11001000 3
b10001000 0
b11101010 4
b10011010 1
b1000100011001000 9
b1000100011001000 6
1(
1.
b101 &
b11101010 %
b10011010 $
b1001101011101010 !
b1001101011101010 ,
1)
1+
#525720
0)
0+
#532460
b111110001111 #
b111110001111 -
b111110001111 5
b1100 4
b10101100 1
b11101010 3
b10011010 0
b1100 %
b10101100 $
b1010110000001100 !
b1010110000001100 ,
b110 &
0(
0.
b1001101011101010 6
1)
1+
#539200
0)
0+
#545940
b1010110000001100 #
b1010110000001100 -
b1010110000001100 5
b1100 3
b10101100 0
b101110 4
b10111110 1
b1010110000001100 9
b1010110000001100 6
1(
1.
b111 &
b101110 %
b10111110 $
b1011111000101110 !
b1011111000101110 ,
1)
1+
#552680
0)
0+
#559420
b111110001111 #
b111110001111 -
b111110001111 5
b1010000 4
b11010000 1
b101110 3
b10111110 0
b1010000 %
b11010000 $
b1101000001010000 !
b1101000001010000 ,
b1000 &
0(
0.
b1011111000101110 6
1)
1+
#566160
0)
0+
#572900
b1101000001010000 #
b1101000001010000 -
b1101000001010000 5
b1010000 3
b11010000 0
b1110010 4
b11100010 1
b1101000001010000 9
b1101000001010000 6
1(
1.
b1001 &
b1110010 %
b11100010 $
b1110001001110010 !
b1110001001110010 ,
1)
1+
#579640
0)
0+
#586380
b111110001111 #
b111110001111 -
b111110001111 5
b10010100 4
b11110100 1
b1110010 3
b11100010 0
b10010100 %
b11110100 $
b1111010010010100 !
b1111010010010100 ,
b1010 &
0(
0.
b1110001001110010 6
1)
1+
#593120
0)
0+
#599860
b1111010010010100 #
b1111010010010100 -
b1111010010010100 5
b10010100 3
b11110100 0
b10110110 4
b110 1
b1111010010010100 9
b1111010010010100 6
1(
1.
b1011 &
b10110110 %
b110 $
b11010110110 !
b11010110110 ,
1)
1+
#606600
0)
0+
#613340
b1110111110001111 #
b1110111110001111 -
b1110111110001111 5
b11011000 4
b11000 1
b10110110 3
b110 0
b11011000 %
b11000 $
b1100011011000 !
b1100011011000 ,
b1100 &
0(
0.
b11111101111 7
b11010110110 6
1)
1+
#620080
0)
0+
#626820
b1100011011000 #
b1100011011000 -
b1100011011000 5
b11011000 3
b11000 0
b11111010 4
b101010 1
b1100011011000 9
b1100011011000 6
1(
1.
b1101 &
b11111010 %
b101010 $
b10101011111010 !
b10101011111010 ,
1)
1+
#633560
0)
0+
#640300
b111110001111 #
b111110001111 -
b111110001111 5
b11100 4
b111100 1
b11111010 3
b101010 0
b11100 %
b111100 $
b11110000011100 !
b11110000011100 ,
b1110 &
0(
0.
b100001111 7
b10101011111010 6
1)
1+
#647040
0)
0+
#653780
b11110000011100 #
b11110000011100 -
b11110000011100 5
b11100 3
b111100 0
b111110 4
b1001110 1
b11110000011100 9
b11110000011100 6
1(
1.
b1111 &
b111110 %
b1001110 $
b100111000111110 !
b100111000111110 ,
1)
1+
#660520
0)
0+
#667260
b111110001111 #
b111110001111 -
b111110001111 5
b1100000 4
b1100000 1
b111110 3
b1001110 0
b1100000 %
b1100000 $
b110000001100000 !
b110000001100000 ,
b0 &
0(
0.
b100111000111110 6
1)
1+
#674000
0)
0+
#680740
b110000001100000 #
b110000001100000 -
b110000001100000 5
b1100000 3
b1100000 0
b10000010 4
b1110010 1
b110000001100000 9
b110000001100000 6
1(
1.
b1 &
b10000010 %
b1110010 $
b111001010000010 !
b111001010000010 ,
1)
1+
#687480
0)
0+
#694220
b111110001111 #
b111110001111 -
b111110001111 5
b10100100 4
b10000100 1
b10000010 3
b1110010 0
b10100100 %
b10000100 $
b1000010010100100 !
b1000010010100100 ,
0'
0/
b10 &
0(
0.
b111001010000010 6
1)
1+
#700960
0)
0+
#707700
b1000010010100100 5
b10100100 3
b10000100 0
b0 #
b0 -
b11000110 4
b10010110 1
b1000010010100100 9
b1000010010100100 6
08
0"
1(
1.
b11 &
b11000110 %
b10010110 $
b1001011011000110 !
b1001011011000110 ,
1)
1+
#714440
0)
0+
#721180
b111110001111 5
b11101000 4
b10101000 1
b11000110 3
b10010110 0
b11101000 %
b10101000 $
b1010100011101000 !
b1010100011101000 ,
b100 &
0(
0.
b1001011011000110 6
1)
1+
#727920
0)
0+
#734660
b1010100011101000 5
b11101000 3
b10101000 0
b1010 4
b10111010 1
b1010100011101000 9
b1010100011101000 6
1(
1.
b101 &
b1010 %
b10111010 $
b1011101000001010 !
b1011101000001010 ,
1)
1+
#741400
0)
0+
#748140
b111101101111 5
b101100 4
b11001100 1
b1010 3
b10111010 0
b101100 %
b11001100 $
b1100110000101100 !
b1100110000101100 ,
b110 &
0(
0.
b11101101111 :
b1011101000001010 6
1)
1+
#754880
0)
0+
#761620
b1100110000101100 5
b101100 3
b11001100 0
b1001110 4
b11011110 1
b1100110000101100 9
b1100110000101100 6
1(
1.
b111 &
b1001110 %
b11011110 $
b1101111001001110 !
b1101111001001110 ,
1)
1+
#768360
0)
0+
#775100
b111110001111 5
b1110000 4
b11110000 1
b1001110 3
b11011110 0
b1110000 %
b11110000 $
b1111000001110000 !
b1111000001110000 ,
b1000 &
0(
0.
b110001111 :
b1101111001001110 6
1)
1+
#781840
0)
0+
#788580
b1111000001110000 5
b1110000 3
b11110000 0
b10010010 4
b10 1
b1111000001110000 9
b1111000001110000 6
1(
1.
b1001 &
b10010010 %
b10 $
b1010010010 !
b1010010010 ,
1)
1+
#795320
0)
0+
#802060
b1110111110001111 5
b10110100 4
b10100 1
b10010010 3
b10 0
b10110100 %
b10100 $
b1010010110100 !
b1010010110100 ,
b1010 &
0(
0.
b11111101111 7
b1010010010 6
1)
1+
#808800
0)
0+
#815540
b1010010110100 5
b10110100 3
b10100 0
b11010110 4
b100110 1
b1010010110100 9
b1010010110100 6
1(
1.
b1011 &
b11010110 %
b100110 $
b10011011010110 !
b10011011010110 ,
1)
1+
#822280
0)
0+
#829020
b111110001111 5
b11111000 4
b111000 1
b11010110 3
b100110 0
b11111000 %
b111000 $
b11100011111000 !
b11100011111000 ,
b1100 &
0(
0.
b100001111 7
b10011011010110 6
1)
1+
#835760
0)
0+
#842500
b11100011111000 5
b11111000 3
b111000 0
b11010 4
b1001010 1
b11100011111000 9
b11100011111000 6
1(
1.
b1101 &
b11010 %
b1001010 $
b100101000011010 !
b100101000011010 ,
1)
1+
#849240
0)
0+
#855980
b111101101111 5
b111100 4
b1011100 1
b11010 3
b1001010 0
b111100 %
b1011100 $
b101110000111100 !
b101110000111100 ,
b1110 &
0(
0.
b11101101111 :
b100101000011010 6
1)
1+
#862720
0)
0+
#869460
b101110000111100 5
b111100 3
b1011100 0
b1011110 4
b1101110 1
b101110000111100 9
b101110000111100 6
1(
1.
b1111 &
b1011110 %
b1101110 $
b110111001011110 !
b110111001011110 ,
1)
1+
#876200
0)
0+
#882940
b111110001111 5
b10000000 4
b10000000 1
b1011110 3
b1101110 0
b10000000 %
b10000000 $
b1000000010000000 !
b1000000010000000 ,
b0 &
0(
0.
b110001111 :
b110111001011110 6
1)
1+
#889680
0)
0+
#896420
b1000000010000000 5
b10000000 3
b10000000 0
b10100010 4
b10010010 1
b1000000010000000 9
b1000000010000000 6
1(
1.
b1 &
b10100010 %
b10010010 $
b1001001010100010 !
b1001001010100010 ,
1)
1+
#903160
0)
0+
#909900
b111110001111 5
b11000100 4
b10100100 1
b10100010 3
b10010010 0
b11000100 %
b10100100 $
b1010010011000100 !
b1010010011000100 ,
1'
1/
b10 &
0(
0.
b1001001010100010 6
1)
1+
#916640
0)
0+
#923380
b1010010011000100 5
b11000100 3
b10100100 0
b1010010011000100 #
b1010010011000100 -
b11100110 4
b10110110 1
b1010010011000100 9
b1010010011000100 6
18
1"
1(
1.
b11 &
b11100110 %
b10110110 $
b1011011011100110 !
b1011011011100110 ,
1)
1+
#930120
0)
0+
#936860
b111110001111 #
b111110001111 -
b111110001111 5
b1000 4
b11001000 1
b11100110 3
b10110110 0
b1000 %
b11001000 $
b1100100000001000 !
b1100100000001000 ,
b100 &
0(
0.
b1011011011100110 6
1)
1+
#943600
0)
0+
#950340
b1100100000001000 #
b1100100000001000 -
b1100100000001000 5
b1000 3
b11001000 0
b101010 4
b11011010 1
b1100100000001000 9
b1100100000001000 6
1(
1.
b101 &
b101010 %
b11011010 $
b1101101000101010 !
b1101101000101010 ,
1)
1+
#957080
0)
0+
#963820
b111110001111 #
b111110001111 -
b111110001111 5
b1001100 4
b11101100 1
b101010 3
b11011010 0
b1001100 %
b11101100 $
b1110110001001100 !
b1110110001001100 ,
b110 &
0(
0.
b1101101000101010 6
1)
1+
#970560
0)
0+
#977300
b1110110001001100 #
b1110110001001100 -
b1110110001001100 5
b1001100 3
b11101100 0
b1101110 4
b11111110 1
b1110110001001100 9
b1110110001001100 6
1(
1.
b111 &
b1101110 %
b11111110 $
b1111111001101110 !
b1111111001101110 ,
1)
1+
#984040
0)
0+
#990780
b111110001111 #
b111110001111 -
b111110001111 5
b10010000 4
b10000 1
b1101110 3
b11111110 0
b10010000 %
b10000 $
b1000010010000 !
b1000010010000 ,
b1000 &
0(
0.
b1111111001101110 6
1)
1+
#997520
0)
0+
#1004260
b1000010010000 #
b1000010010000 -
b1000010010000 5
b10010000 3
b10000 0
b10110010 4
b100010 1
b1000010010000 9
b1000010010000 6
1(
1.
b1001 &
b10110010 %
b100010 $
b10001010110010 !
b10001010110010 ,
1)
1+
#1011000
0)
0+
#1017740
b111110001111 #
b111110001111 -
b111110001111 5
b11010100 4
b110100 1
b10110010 3
b100010 0
b11010100 %
b110100 $
b11010011010100 !
b11010011010100 ,
b1010 &
0(
0.
b10001010110010 6
1)
1+
#1024480
0)
0+
#1031220
b11010011010100 #
b11010011010100 -
b11010011010100 5
b11010100 3
b110100 0
b11110110 4
b1000110 1
b11010011010100 9
b11010011010100 6
1(
1.
b1011 &
b11110110 %
b1000110 $
b100011011110110 !
b100011011110110 ,
1)
1+
#1037960
0)
0+
#1044700
b111110001111 #
b111110001111 -
b111110001111 5
b11000 4
b1011000 1
b11110110 3
b1000110 0
b11000 %
b1011000 $
b101100000011000 !
b101100000011000 ,
b1100 &
0(
0.
b100011011110110 6
1)
1+
#1051440
0)
0+
#1058180
b101100000011000 #
b101100000011000 -
b101100000011000 5
b11000 3
b1011000 0
b111010 4
b1101010 1
b101100000011000 9
b101100000011000 6
1(
1.
b1101 &
b111010 %
b1101010 $
b110101000111010 !
b110101000111010 ,
1)
1+
#1064920
0)
0+
#1071660
b111110001111 #
b111110001111 -
b111110001111 5
b1011100 4
b1111100 1
b111010 3
b1101010 0
b1011100 %
b1111100 $
b111110001011100 !
b111110001011100 ,
b1110 &
0(
0.
b110101000111010 6
1)
1+
#1078400
0)
0+
#1085140
b111110001011100 #
b111110001011100 -
b111110001011100 5
b1011100 3
b1111100 0
b1111110 4
b10001110 1
b111110001011100 9
b111110001011100 6
1(
1.
b1111 &
b1111110 %
b10001110 $
b1000111001111110 !
b1000111001111110 ,
1)
1+
#1091880
0)
0+
#1098620
b111110001111 #
b111110001111 -
b111110001111 5
b10100000 4
b10100000 1
b1111110 3
b10001110 0
b10100000 %
b10100000 $
b1010000010100000 !
b1010000010100000 ,
b0 &
0(
0.
b1000111001111110 6
1)
1+
#1105360
0)
0+
#1112100
b1010000010100000 #
b1010000010100000 -
b1010000010100000 5
b10100000 3
b10100000 0
b11000010 4
b10110010 1
b1010000010100000 9
b1010000010100000 6
1(
1.
b1 &
b11000010 %
b10110010 $
b1011001011000010 !
b1011001011000010 ,
1)
1+
#1118840
0)
0+
#1125580
b111110001111 #
b111110001111 -
b111110001111 5
b11100100 4
b11000100 1
b11000010 3
b10110010 0
b11100100 %
b11000100 $
b1100010011100100 !
b1100010011100100 ,
0'
0/
b10 &
0(
0.
b1011001011000010 6
1)
1+
#1132320
0)
0+
#1139060
b1100010011100100 5
b11100100 3
b11000100 0
b0 #
b0 -
b110 4
b11010110 1
b1100010011100100 9
b1100010011100100 6
08
0"
1(
1.
b11 &
b110 %
b11010110 $
b1101011000000110 !
b1101011000000110 ,
1)
1+
#1145800
0)
0+
#1152540
b111101101111 5
b101000 4
b11101000 1
b110 3
b11010110 0
b101000 %
b11101000 $
b1110100000101000 !
b1110100000101000 ,
b100 &
0(
0.
b11101101111 :
b1101011000000110 6
1)
1+
#1159280
0)
0+
#1166020
b1110100000101000 5
b101000 3
b11101000 0
b1001010 4
b11111010 1
b1110100000101000 9
b1110100000101000 6
1(
1.
b101 &
b1001010 %
b11111010 $
b1111101001001010 !
b1111101001001010 ,
1)
1+
#1172760
0)
0+
#1179500
b111110001111 5
b1101100 4
b1100 1
b1001010 3
b11111010 0
b1101100 %
b1100 $
b110001101100 !
b110001101100 ,
b110 &
0(
0.
b110001111 :
b1111101001001010 6
1)
1+
#1186240
0)
0+
#1192980
b110001101100 5
b1101100 3
b1100 0
b10001110 4
b11110 1
b110001101100 9
b110001101100 6
1(
1.
b111 &
b10001110 %
b11110 $
b1111010001110 !
b1111010001110 ,
1)
1+
#1199720
0)
0+
#1206460
b111110001111 5
b10110000 4
b110000 1
b10001110 3
b11110 0
b10110000 %
b110000 $
b11000010110000 !
b11000010110000 ,
b1000 &
0(
0.
b1111010001110 6
1)
1+
#1213200
0)
0+
#1219940
b11000010110000 5
b10110000 3
b110000 0
b11010010 4
b1000010 1
b11000010110000 9
b11000010110000 6
1(
1.
b1001 &
b11010010 %
b1000010 $
b100001011010010 !
b100001011010010 ,
1)
1+
#1226680
0)
0+
#1233420
b111110001111 5
b11110100 4
b1010100 1
b11010010 3
b1000010 0
b11110100 %
b1010100 $
b101010011110100 !
b101010011110100 ,
b1010 &
0(
0.
b100001011010010 6
1)
1+
#1240160
0)
0+
#1246900
b101010011110100 5
b11110100 3
b1010100 0
b10110 4
b1100110 1
b101010011110100 9
b101010011110100 6
1(
1.
b1011 &
b10110 %
b1100110 $
b110011000010110 !
b110011000010110 ,
1)
1+
#1253640
0)
0+
#1260380
b111101101111 5
b111000 4
b1111000 1
b10110 3
b1100110 0
b111000 %
b1111000 $
b111100000111000 !
b111100000111000 ,
b1100 &
0(
0.
b11101101111 :
b110011000010110 6
1)
1+
#1267120
0)
0+
#1273860
b111100000111000 5
b111000 3
b1111000 0
b1011010 4
b10001010 1
b111100000111000 9
b111100000111000 6
1(
1.
b1101 &
b1011010 %
b10001010 $
b1000101001011010 !
b1000101001011010 ,
1)
1+
#1280600
0)
0+
#1287340
b111110001111 5
b1111100 4
b10011100 1
b1011010 3
b10001010 0
b1111100 %
b10011100 $
b1001110001111100 !
b1001110001111100 ,
b1110 &
0(
0.
b110001111 :
b1000101001011010 6
1)
1+
#1294080
0)
0+
#1300820
b1001110001111100 5
b1111100 3
b10011100 0
b10011110 4
b10101110 1
b1001110001111100 9
b1001110001111100 6
1(
1.
b1111 &
b10011110 %
b10101110 $
b1010111010011110 !
b1010111010011110 ,
1)
1+
#1307560
0)
0+
#1314300
b111110001111 5
b11000000 4
b11000000 1
b10011110 3
b10101110 0
b11000000 %
b11000000 $
b1100000011000000 !
b1100000011000000 ,
b0 &
0(
0.
b1010111010011110 6
1)
1+
#1321040
0)
0+
#1327780
b1100000011000000 5
b11000000 3
b11000000 0
b11100010 4
b11010010 1
b1100000011000000 9
b1100000011000000 6
1(
1.
b1 &
b11100010 %
b11010010 $
b1101001011100010 !
b1101001011100010 ,
1)
1+
#1334520
0)
0+
#1341260
b111110001111 5
b100 4
b11100100 1
b11100010 3
b11010010 0
b100 %
b11100100 $
b1110010000000100 !
b1110010000000100 ,
1'
1/
b10 &
0(
0.
b1101001011100010 6
1)
1+
#1348000
0)
0+
#1354740
b1110010000000100 5
b100 3
b11100100 0
b1110010000000100 #
b1110010000000100 -
b100110 4
b11110110 1
b1110010000000100 9
b1110010000000100 6
18
1"
1(
1.
b11 &
b100110 %
b11110110 $
b1111011000100110 !
b1111011000100110 ,
1)
1+
#1361480
0)
0+
#1368220
b111110001111 #
b111110001111 -
b111110001111 5
b1001000 4
b1000 1
b100110 3
b11110110 0
b1001000 %
b1000 $
b100001001000 !
b100001001000 ,
b100 &
0(
0.
b1111011000100110 6
1)
1+
#1374960
0)
0+
